{
  "message_id": "19ddb0ac35d448d9",
  "subject": "AI를 쓰는 회사'는 끝났다. 이제 'AI로 돌아가는 회사'의 시대",
  "from": "\"AI 코리아 커뮤니티 뉴스레터 팀\" <ai-korea-community@ghost.io>",
  "date": "Wed, 29 Apr 2026 21:00:09 +0000",
  "date_kst": "2026-04-30 06:00:09",
  "gmail_labels": [
    "IT",
    "CATEGORY_UPDATES"
  ],
  "html_length": 85392,
  "html_body": "<!doctype html>\r\n<html>\r\n    <head>\r\n        <meta name=\"viewport\" content=\"width=device-width\">\r\n        <meta http-equiv=\"Content-Type\" content=\"text/html; charset=UTF-8\">\r\n        <!--[if mso]><xml><o:OfficeDocumentSettings><o:PixelsPerInch>96</o:PixelsPerInch><o:AllowPNG/></o:OfficeDocumentSettings></xml><![endif]-->\r\n        <title>AI&#xB97C; &#xC4F0;&#xB294; &#xD68C;&#xC0AC;&#39;&#xB294; &#xB05D;&#xB0AC;&#xB2E4;. &#xC774;&#xC81C; &#39;AI&#xB85C; &#xB3CC;&#xC544;&#xAC00;&#xB294; &#xD68C;&#xC0AC;&#39;&#xC758; &#xC2DC;&#xB300;</title>\r\n        <style>\r\n@media only screen and (max-width: 620px) {\r\n  table.body {\r\n    width: 100%;\r\n    min-width: 100%;\r\n  }\r\n\r\n  table.body .content {\r\n    padding: 0 !important;\r\n  }\r\n\r\n  table.body .container {\r\n    padding: 0 !important;\r\n    width: 100% !important;\r\n  }\r\n\r\n  table.body .main {\r\n    border-spacing: 10px 0 !important;\r\n    border-left-width: 0 !important;\r\n    border-radius: 0 !important;\r\n    border-right-width: 0 !important;\r\n  }\r\n\r\n  table.body .img-responsive {\r\n    height: auto !important;\r\n    max-width: 100% !important;\r\n    width: auto !important;\r\n  }\r\n}\r\n@media all {\r\n  .ExternalClass {\r\n    width: 100%;\r\n  }\r\n\r\n  .ExternalClass,\r\n.ExternalClass p,\r\n.ExternalClass span,\r\n.ExternalClass font,\r\n.ExternalClass td,\r\n.ExternalClass div {\r\n    line-height: 100%;\r\n  }\r\n\r\n  .apple-link a {\r\n    color: inherit !important;\r\n    font-family: inherit !important;\r\n    font-size: inherit !important;\r\n    font-weight: inherit !important;\r\n    line-height: inherit !important;\r\n    text-decoration: none !important;\r\n  }\r\n\r\n  #MessageViewBody a {\r\n    color: inherit;\r\n    text-decoration: none;\r\n    font-size: inherit;\r\n    font-family: inherit;\r\n    font-weight: inherit;\r\n    line-height: inherit;\r\n  }\r\n}\r\n@media only screen and (max-width: 620px) {\r\n  table[class=body] h1 {\r\n    font-size: 28px !important;\r\n    margin-bottom: 10px !important;\r\n  }\r\n\r\n  table[class=body] p,\r\ntable[class=body] ul,\r\ntable[class=body] ol,\r\ntable[class=body] td,\r\ntable[class=body] span,\r\ntable[class=body] a {\r\n    font-size: 16px !important;\r\n  }\r\n\r\n  table[class=body] .wrapper,\r\ntable[class=body] .article {\r\n    padding: 10px !important;\r\n  }\r\n\r\n  table[class=body] .content {\r\n    padding: 0 !important;\r\n  }\r\n\r\n  table[class=body] .container {\r\n    padding: 0 !important;\r\n    width: 100% !important;\r\n  }\r\n\r\n  table[class=body] .main {\r\n    border-left-width: 0 !important;\r\n    border-radius: 0 !important;\r\n    border-right-width: 0 !important;\r\n  }\r\n\r\n  table[class=body] .btn table {\r\n    width: 100% !important;\r\n  }\r\n\r\n  table[class=body] .btn a {\r\n    width: 100% !important;\r\n  }\r\n\r\n  table[class=body] .img-responsive {\r\n    height: auto !important;\r\n    max-width: 100% !important;\r\n    width: auto !important;\r\n  }\r\n\r\n  table[class=body] p[class=small],\r\ntable[class=body] a[class=small] {\r\n    font-size: 11px !important;\r\n  }\r\n}\r\n.kg-nft-link {\r\n  display: block;\r\n  text-decoration: none !important;\r\n  color: #15212A !important;\r\n  font-family: inherit !important;\r\n  font-size: 14px;\r\n  line-height: 1.3;\r\n  padding-top: 4px;\r\n  padding-right: 20px;\r\n  padding-left: 20px;\r\n  padding-bottom: 4px;\r\n}\r\n.kg-twitter-link {\r\n  display: block;\r\n  text-decoration: none !important;\r\n  color: #15212A !important;\r\n  font-family: inherit !important;\r\n  font-size: 15px;\r\n  padding: 8px;\r\n  line-height: 1.3;\r\n}\r\n.kg-cta-link-accent .kg-cta-sponsor-label a {\r\n  color: #45e600 !important;\r\n}\r\n.kg-cta-text a:not(.kg-cta-link-accent .kg-cta-text a) {\r\n  color: #15212A;\r\n  text-decoration: underline;\r\n}\r\n.kg-cta-link-accent .kg-cta-text a {\r\n  color: #45e600 !important;\r\n}\r\n@media only screen and (max-width: 620px) {\r\n  table.body .kg-bookmark-card {\r\n    width: 90vw;\r\n  }\r\n\r\n  table.body .kg-bookmark-thumbnail {\r\n    display: none !important;\r\n  }\r\n\r\n  table.body .kg-bookmark-metadata span {\r\n    font-size: 13px !important;\r\n  }\r\n\r\n  table.body .kg-embed-card {\r\n    max-width: 90vw !important;\r\n  }\r\n\r\n  table.body .kg-cta-card {\r\n    padding: 0 20px;\r\n  }\r\n\r\n  table.body .kg-cta-card.kg-cta-bg-none {\r\n    padding: 0;\r\n  }\r\n\r\n  table.body .kg-cta-sponsor-label {\r\n    padding: 10px 0;\r\n  }\r\n\r\n  table.body table.kg-cta-content-wrapper:not(.kg-cta-bg-none.kg-cta-no-dividers table.kg-cta-content-wrapper) {\r\n    padding: 20px 0;\r\n  }\r\n\r\n  table.body .kg-cta-immersive.kg-cta-has-img:not(.kg-cta-bg-none):not(.kg-cta-no-label) table.kg-cta-content-wrapper {\r\n    padding-top: 0;\r\n  }\r\n\r\n  table.body .kg-cta-minimal .kg-cta-image-container {\r\n    padding-right: 20px;\r\n  }\r\n\r\n  table.body .kg-cta-immersive .kg-cta-image-container {\r\n    padding-bottom: 20px;\r\n  }\r\n\r\n  table.body .kg-cta-immersive.kg-cta-no-text .kg-cta-image-container {\r\n    padding-bottom: 0;\r\n  }\r\n\r\n  table.body .kg-cta-button-container {\r\n    padding-top: 16px;\r\n  }\r\n\r\n  table.body .kg-cta-minimal .kg-cta-image-container {\r\n    display: inline-block !important;\r\n    width: 100% !important;\r\n    padding: 0 !important;\r\n    padding-bottom: 16px !important;\r\n    padding-right: 0 !important;\r\n  }\r\n\r\n  table.body .kg-cta-minimal .kg-cta-content-inner {\r\n    display: inline-block !important;\r\n    width: 100% !important;\r\n    padding: 0 !important;\r\n  }\r\n\r\n  table.body .kg-cta-minimal img.kg-cta-image {\r\n    width: 52px !important;\r\n    height: 52px !important;\r\n  }\r\n}\r\n@media all {\r\n  .ExternalClass {\r\n    width: 100%;\r\n  }\r\n\r\n  .ExternalClass,\r\n.ExternalClass p,\r\n.ExternalClass span,\r\n.ExternalClass font,\r\n.ExternalClass td,\r\n.ExternalClass div {\r\n    line-height: 100%;\r\n  }\r\n\r\n  .recipient-link a {\r\n    color: inherit !important;\r\n    font-family: inherit !important;\r\n    font-size: inherit !important;\r\n    font-weight: inherit !important;\r\n    line-height: inherit !important;\r\n    text-decoration: none !important;\r\n  }\r\n\r\n  #MessageViewBody a {\r\n    color: inherit;\r\n    text-decoration: none;\r\n    font-size: inherit;\r\n    font-family: inherit;\r\n    font-weight: inherit;\r\n    line-height: inherit;\r\n  }\r\n}\r\n.post-title-link {\r\n  display: block;\r\n  margin-top: 32px;\r\n  color: #15212A;\r\n  text-align: center;\r\n  line-height: 1.1;\r\n}\r\n.post-title-link-left {\r\n  text-align: left;\r\n}\r\n.view-online-link {\r\n  word-wrap: none;\r\n  white-space: nowrap;\r\n  color: #15212a;\r\n  color: rgba(0, 0, 0, 0.6);\r\n  text-decoration: underline !important;\r\n}\r\n.kg-audio-link {\r\n  color: #15212a !important;\r\n  color: rgba(0, 0, 0, 0.6) !important;\r\n}\r\n@media only screen and (max-width: 620px) {\r\n  .hide-mobile {\r\n    display: none;\r\n  }\r\n\r\n  .mobile-only {\r\n    display: initial !important;\r\n  }\r\n\r\n  .hide-desktop {\r\n    display: initial !important;\r\n  }\r\n\r\n  .desktop-only {\r\n    display: none !important;\r\n  }\r\n\r\n  table.body p,\r\ntable.body ul,\r\ntable.body ol,\r\ntable.body td {\r\n    font-size: 16px;\r\n  }\r\n\r\n  table.header .post-excerpt {\r\n    font-size: 16px !important;\r\n  }\r\n\r\n  table.body .kg-callout-card {\r\n    padding: 16px 24px !important;\r\n  }\r\n\r\n  table.body .kg-callout-text {\r\n    font-size: 16px !important;\r\n    line-height: 1.5 !important;\r\n  }\r\n\r\n  table.body pre {\r\n    white-space: pre-wrap !important;\r\n    word-break: break-word !important;\r\n  }\r\n\r\n  table.body .main,\r\ntable.header .header-main {\r\n    border-spacing: 10px 0 !important;\r\n    border-left-width: 0 !important;\r\n    border-radius: 0 !important;\r\n    border-right-width: 0 !important;\r\n  }\r\n\r\n  table.header .site-icon {\r\n    padding-top: 0 !important;\r\n  }\r\n\r\n  table.header .site-info {\r\n    padding-top: 24px !important;\r\n  }\r\n\r\n  table.header .post-title-link {\r\n    margin-top: 24px !important;\r\n  }\r\n\r\n  table.header .post-meta-wrapper {\r\n    padding-bottom: 24px !important;\r\n  }\r\n\r\n  table.header .site-icon img {\r\n    width: 36px !important;\r\n    height: 36px !important;\r\n  }\r\n\r\n  table.header .site-url a {\r\n    font-size: 13px !important;\r\n    padding-bottom: 16px !important;\r\n  }\r\n\r\n  table.header .post-meta,\r\ntable.header .post-meta-date {\r\n    white-space: normal !important;\r\n    font-size: 13px !important;\r\n    line-height: 1.2;\r\n  }\r\n\r\n  table.header .post-meta,\r\ntable.header .view-online {\r\n    width: 100% !important;\r\n  }\r\n\r\n  table.header .post-meta-left,\r\ntable.header .post-meta-left.view-online {\r\n    width: 100% !important;\r\n    text-align: left !important;\r\n  }\r\n\r\n  table.header .post-meta.view-online-mobile {\r\n    display: table-row !important;\r\n  }\r\n\r\n  table.header .post-meta-left.view-online-mobile,\r\ntable.header .post-meta-left.view-online-mobile .view-online {\r\n    text-align: left !important;\r\n  }\r\n\r\n  table.header .post-meta.view-online.desktop {\r\n    display: none !important;\r\n  }\r\n\r\n  table.header .view-online {\r\n    text-decoration: underline;\r\n  }\r\n\r\n  table.body .footer p,\r\ntable.body .footer p span {\r\n    font-size: 13px !important;\r\n  }\r\n\r\n  table.header .view-online-link,\r\ntable.body .footer,\r\ntable.body .footer a {\r\n    font-size: 13px !important;\r\n  }\r\n\r\n  table.header .post-title a {\r\n    font-size: 26px !important;\r\n    line-height: 1.1 !important;\r\n  }\r\n\r\n  table.feedback-buttons {\r\n    display: table !important;\r\n    width: 100% !important;\r\n    max-width: 390px;\r\n  }\r\n\r\n  table.feedback-buttons img {\r\n    display: inherit !important;\r\n  }\r\n\r\n  table.body .feedback-button-text {\r\n    display: none!important;\r\n  }\r\n\r\n  table.body .latest-posts-header {\r\n    font-size: 12px !important;\r\n  }\r\n\r\n  table.body .latest-post-title {\r\n    padding-right: 8px !important;\r\n  }\r\n\r\n  table.body .latest-post h4,\r\ntable.body .latest-post h4 span {\r\n    padding: 4px 0 6px !important;\r\n    font-size: 15px !important;\r\n  }\r\n\r\n  table.body .latest-post-excerpt,\r\ntable.body .latest-post-excerpt a,\r\ntable.body .latest-post-excerpt span {\r\n    font-size: 13px !important;\r\n    line-height: 1.2 !important;\r\n  }\r\n\r\n  table.body .subscription-box h3 {\r\n    font-size: 14px !important;\r\n  }\r\n\r\n  table.body .subscription-box p,\r\ntable.body .subscription-box p span {\r\n    font-size: 13px !important;\r\n  }\r\n\r\n  table.body .subscription-details,\r\ntable.body .manage-subscription {\r\n    display: inline-block;\r\n    width: 100%;\r\n    text-align: left !important;\r\n    font-size: 13px !important;\r\n  }\r\n\r\n  table.body .subscription-details {\r\n    padding-bottom: 12px;\r\n  }\r\n\r\n  table.body h1 {\r\n    font-size: 32px !important;\r\n    line-height: 1.3 !important;\r\n  }\r\n\r\n  table.body h2,\r\ntable.body h2 span {\r\n    font-size: 26px !important;\r\n    line-height: 1.22 !important;\r\n  }\r\n\r\n  table.body h3 {\r\n    font-size: 21px !important;\r\n    line-height: 1.25 !important;\r\n  }\r\n\r\n  table.body h4 {\r\n    font-size: 19px !important;\r\n    line-height: 1.3 !important;\r\n  }\r\n\r\n  table.body h5 {\r\n    font-size: 16px !important;\r\n    line-height: 1.4 !important;\r\n  }\r\n\r\n  table.body h6 {\r\n    font-size: 16px !important;\r\n    line-height: 1.4 !important;\r\n  }\r\n\r\n  table.body blockquote {\r\n    font-size: 16px !important;\r\n    line-height: 1.6;\r\n    margin-bottom: 0;\r\n  }\r\n\r\n  table.body blockquote p {\r\n    margin-right: 15px !important;\r\n    margin-left: 15px !important;\r\n  }\r\n\r\n  table.body blockquote.kg-blockquote-alt {\r\n    border-left: 0 none !important;\r\n    margin: 0 !important;\r\n    font-size: 18px !important;\r\n    line-height: 1.4 !important;\r\n  }\r\n\r\n  table.body blockquote.kg-blockquote-alt p {\r\n    margin-right: 20px !important;\r\n    margin-left: 20px !important;\r\n  }\r\n\r\n  table.body hr {\r\n    margin: 2em 0 !important;\r\n  }\r\n\r\n  .feature-image-caption {\r\n    font-size: 13px!important;\r\n  }\r\n\r\n  .kg-card-figcaption {\r\n    font-size: 13px!important;\r\n  }\r\n\r\n  .kg-card-figcaption p,\r\n.kg-card-figcaption p span {\r\n    font-size: 13px!important;\r\n  }\r\n}\r\n@media all {\r\n  .subscription-details p.hidden {\r\n    display: none !important;\r\n  }\r\n}\r\n</style>\r\n        <!--[if mso]>\r\n        <style type=\"text/css\">\r\n            ul, ol { margin-left: 1.5em !important; } \r\n        </style>\r\n        <![endif]-->\r\n    </head>\r\n    <body data-testid=\"email-preview-body\" style=\"background-color: #fff; font-family: -apple-system, BlinkMacSystemFont, Roboto, Helvetica, Arial, sans-serif; -webkit-font-smoothing: antialiased; font-size: 18px; line-height: 0; margin: 0; padding: 0; -ms-text-size-adjust: 100%; -webkit-text-size-adjust: 100%; color: #15212A;\"><img width=\"1\" height=\"1\" alt=\"\" src=\"https://email.m.ghost.io/o/eJw8jkGKwzAMAF-zviXIiiJZBz3GttzUbBJDmxb298v2sMdhGBg3KV5jCs2iiJAyq4R25L5P3Y31hhJXYMBGKwDEtjCnGO7mGRQpcall8eVWHVNj0ZjRMwly6IaADISKEQB0xgVdAKo4YWsKXwTHvN3H85r7CA97vs7tZ4xzpfXPnfndHnMdR7isvPbv6XMVLvsk_1T2sU3KlCCGt-FvAAAA__9Umjwj\">\r\n        <span class=\"preheader\" style=\"color: transparent; display: none; height: 0; max-height: 0; max-width: 0; opacity: 0; overflow: hidden; mso-hide: all; visibility: hidden; width: 0;\">&#xC5D0;&#xCF54; &#xBA64;&#xBC84;&#xB2D8;&#xB4E4;,\r\n\r\n&#xC798; &#xC9C0;&#xB0B4;&#xACE0; &#xACC4;&#xC2E0;&#xAC00;&#xC694;? &#xC624;&#xB298;&#xB3C4; &#xCD5C;&#xADFC; AI &#xAD00;&#xB828; &#xC18C;&#xC2DD; &#xC911;&#xC5D0;&#xC11C; &#xD568;&#xAED8; &#xAE4A;&#xC774; &#xC0DD;&#xAC01;&#xD574;&#xBCFC;&#xB9CC;&#xD55C; &#xB0B4;&#xC6A9;&#xC744; &#xB4E4;&#xACE0;&#xC654;&#xC2B5;&#xB2C8;&#xB2E4;. &#xC2E4;&#xB9AC;&#xCF58;&#xBC38;&#xB9AC;&#xC758; &#xAC00;&#xC7A5; &#xC601;&#xD5A5;&#xB825; &#xC788;&#xB294; &#xC561;&#xC140;&#xB7EC;&#xB808;&#xC774;&#xD130;&#xC778; Y Combinator&#xC758; &#xD30C;&#xD2B8;&#xB108; Diana&#xAC00; &#xCD5C;&#xADFC; &#39;How To Build A Company With AI From The Ground Up(AI&#xB85C; &#xD68C;&#xC0AC;&#xB97C; &#xCC98;&#xC74C;&#xBD80;&#xD130; &#xB2E4;&#xC2DC; &#xC9D3;&#xB294; &#xBC95;)&#39;&#xC774;&#xB77C;&#xB294; &#xC8FC;&#xC81C;&#xB85C; &#xC778;&#xC0AC;&#xC774;&#xD2B8;&#xB97C; &#xACF5;&#xC720;&#xD588;&#xB294;&#xB370;&#xC694;. &#xB2E8;&#xC21C;&#xD788; &#39;AI&#xB97C; &#xC5B4;&#xB5BB;&#xAC8C; &#xC798; &#xC4F8;&#xAE4C;?&#39;&#xB97C; &#xB118;&#xC5B4;&#xC11C;, &#39;&#xD68C;&#xC0AC;&#xB77C;&#xB294; &#xC870;&#xC9C1; &#xC790;&#xCCB4;&#xB97C; AI &#xC704;&#xC5D0; &#xC5B4;&#xB5BB;&#xAC8C; &#xC0C8;&#xB85C; &#xC9C0;&#xC5B4;&#xC57C; &#xD558;&#xB294;&#xAC00;?&#39;&#xC5D0; &#xB300;&#xD55C; &#xAD49;&#xC7A5;&#xD788; &#xBCF8;&#xC9C8;&#xC801;&#xC778; &#xD1B5;&#xCC30;&#xC774; &#xB2F4;&#xACA8;&#xC788;&#xC5B4; &#xC5D0;&#xCF54; &#xB274;&#xC2A4;&#xB808;&#xD130; &#xAD6C;&#xB3C5;&#xC790;&#xB2D8;&#xB4E4;&#xACFC; &#xD568;&#xAED8; &#xB098;&#xB220;&#xBCF4;&#xACE0;&#xC790; &#xD569;&#xB2C8;&#xB2E4;.\r\n\r\n&#xC9C0;&#xAE08; &#xC6B0;&#xB9AC;&#xB294; &#xC0B0;&#xC5C5;&#xD601;&#xBA85; &#xC774;&#xD6C4; &#xAC00;&#xC7A5; &#xD070; &#xC870;&#xC9C1; &#xC6B4;&#xC601;&#xC758; &#xD328;&#xB7EC;&#xB2E4;&#xC784; &#xC804;&#xD658;&#xAE30;&#xB97C; &#xC0B4;&#xACE0; &#xC788;&#xC2B5;&#xB2C8;&#xB2E4;. &#xD765;&#xBBF8;&#xB85C;&#xC6B4; &#xC810;&#xC740;, &#xC774; &#xBCC0;&#xD654;&#xAC00; &#xB2E8;&#xC21C;&#xD788; &#39;&#xC5D4;&#xC9C0;&#xB2C8;&#xC5B4;&#xAC00; &#xCF54;&#xB4DC;&#xB97C; &#xB354; &#xBE68;&#xB9AC; &#xC9E0;&#xB2E4;&#39;&#xAC70;&#xB098; &#39;&#xB9C8;&#xCF00;&#xD130;&#xAC00; &#xCE74;&#xD53C;&#xB97C; &#xB354; &#xBE68;&#xB9AC; &#xC4F4;&#xB2E4;&#39;&#xB294; &#xC218;&#xC900;&#xC758; &#xC0DD;&#xC0B0;&#xC131; &#xD5A5;&#xC0C1;&#xC774; &#xC544;&#xB2C8;&#xB77C;&#xB294; &#xC0AC;&#xC2E4;&#xC785;&#xB2C8;&#xB2E4;. Diana&#xC758; &#xD45C;&#xD604;&#xC744; &#xBE4C;&#xB9AC;&#xBA74;, &#xC6B0;&#xB9AC;&#xAC00; &#xC9C0;&#xAE08; &#xBAA9;&#xB3C4;&#xD558;&#xACE0; &#xC788;&#xB294; &#xAC83;&#xC740; &#39;&#xC0DD;&#xC0B0;&#xC131;&#xC758; </span>\r\n        <!-- SPACING TO AVOID BODY TEXT BEING DUPLICATED IN PREVIEW TEXT -->\r\n        <div style=\"display:none; max-height:0; overflow:hidden; mso-hide: all;\" aria-hidden=\"true\" role=\"presentation\">\r\n            &#x2007;&#x34F; &#x2007;&#x34F; &#x2007;&#x34F; &#x2007;&#x34F; &#x2007;&#x34F; &#x2007;&#x34F; &#x2007;&#x34F; &#x2007;&#x34F; &#x2007;&#x34F; &#x2007;&#x34F; &#x2007;&#x34F; &#x2007;&#x34F; &#x2007;&#x34F; &#x2007;&#x34F; &#x2007;&#x34F; &#x2007;&#x34F; &#x2007;&#x34F; &#x2007;&#x34F; &#x2007;&#x34F; &#x2007;&#x34F; &#x2007;&#x34F; &#x2007;&#x34F; &#x2007;&#x34F; &#x2007;&#x34F; &#x2007;&#x34F; &#x2007;&#x34F; &#x2007;&#x34F; &#x2007;&#x34F; &#x2007;&#x34F; &#x2007;&#x34F; &#x2007;&#x34F; &#x2007;&#x34F; &#x2007;&#x34F; &#x2007;&#x34F; &#x2007;&#x34F; &#x2007;&#x34F; &#x2007;&#x34F; &#x2007;&#x34F; &#x2007;&#x34F; &#x2007;&#x34F; &#x2007;&#x34F; &#x2007;&#x34F; &#x2007;&#x34F; &#x2007;&#x34F; &#x2007;&#x34F; &#x2007;&#x34F; &#x2007;&#x34F; &#x2007;&#x34F; &#x2007;&#x34F; &#x2007;&#x34F; &#x2007;&#x34F; &#x2007;&#x34F; &#x2007;&#x34F; &#x2007;&#x34F; &#x2007;&#x34F; &#x2007;&#x34F; &#x2007;&#x34F; &#x2007;&#x34F; &#x2007;&#x34F; &#x2007;&#x34F; &#x2007;&#x34F; &#x2007;&#x34F; &#x2007;&#x34F; &#x2007;&#x34F; &#x2007;&#x34F; &#x2007;&#x34F; &#x2007;&#x34F; &#x2007;&#x34F; &#x2007;&#x34F; &#x2007;&#x34F; &#x2007;&#x34F; &#x2007;&#x34F; &#x2007;&#x34F; &#x2007;&#x34F; &#x2007;&#x34F; &#x2007;&#x34F; &#x2007;&#x34F; &#x2007;&#x34F; &#x2007;&#x34F; &#x2007;&#x34F; &#x2007;&#x34F; &#x2007;&#x34F; &#x2007;&#x34F; &#x2007;&#x34F; &#x2007;&#x34F; &#x2007;&#x34F; &#x2007;&#x34F; &#x2007;&#x34F; &#x2007;&#x34F; &#x2007;&#x34F; &#x2007;&#x34F; &#x2007;&#x34F; &#x2007;&#x34F; &#x2007;&#x34F; &#x2007;&#x34F; &#x2007;&#x34F; &#x2007;&#x34F; &#x2007;&#x34F; &#x2007;&#x34F; &#x2007;&#x34F; &#x2007;&#x34F; &#x2007;&#x34F; &#x2007;&#x34F; &#x2007;&#x34F; &#x2007;&#x34F; &#x2007;&#x34F; &#x2007;&#x34F; &#x2007;&#x34F; &#x2007;&#x34F; &#x2007;&#x34F; &#x2007;&#x34F; &#x2007;&#x34F; &#x2007;&#x34F; &#x2007;&#x34F; &#x2007;&#x34F; &#x2007;&#x34F; &#x2007;&#x34F; &#x2007;&#x34F; &#x2007;&#x34F; &#x2007;&#x34F; &#x2007;&#x34F; &#x2007;&#x34F; &#x2007;&#x34F; &#x2007;&#x34F; &#x2007;&#x34F; &#x2007;&#x34F; &#x2007;&#x34F; &#x2007;&#x34F; &#x2007;&#x34F; &#x2007;&#x34F; &#x2007;&#x34F; &#x2007;&#x34F; &#x2007;&#x34F; &#x2007;&#x34F; &#x2007;&#x34F; &#x2007;&#x34F; &#x2007;&#x34F; &#x2007;&#x34F; &#x2007;&#x34F; &#x2007;&#x34F; &#x2007;&#x34F; &#x2007;&#x34F; &#x2007;&#x34F; &#x2007;&#x34F; &#x2007;&#x34F; &#x2007;&#x34F; &#x2007;&#x34F; &#x2007;&#x34F; &#x2007;&#x34F; &#x2007;&#x34F; &#xAD; &#xAD; &#xAD; &#xAD; &#xAD; &#xAD; &#xAD; &#xAD; &#xAD; &#xAD; &#xAD; &#xAD; &#xAD; &#xAD; &#xAD; &#xAD; &#xAD; &#xAD; &#xAD; &#xAD; &#xAD; &#xAD; &#xAD; &#xAD; &#xAD; &#xAD; &#xAD; &#xAD; &#xAD; &#xAD; &#xAD; &#xAD; &#xAD; &#xAD; &#xAD; &#xAD; &#xAD; &#xAD; &#xAD; &#xAD; &#xAD; &#xAD; &#xAD; &#xAD; &#xAD; &#xAD; &#xAD; &#xAD; &#xAD; &#xAD; &#xAD; &#xAD; &#xAD; &#xAD; &#xAD; &#xAD; &#xAD; &#xAD; &#xAD; &#xAD; &#xAD; &#xAD; &#xAD; &#xAD; &#xAD; &#xAD; &#xAD; &#xAD; &#xAD; &#xAD; &#xAD; &#xAD; &#xAD; &#xAD; &#xAD; &#xAD; &#xAD; &#xAD; &#xAD; &#xAD; &#xAD; &#xAD; &#xAD; &#xAD; &#xAD; &#xAD; &#xAD; &#xAD; &#xAD; &#xAD; &#xAD; &#xAD; &#xAD; &#xAD; &#xAD; &#xAD; &#xAD; &#xAD; &#xAD; &#xAD; &#xAD; &#xAD; &#xAD; &#xAD; &#xAD; &#xAD; &#xAD; &#xAD; &#xAD; &#xAD; &#xAD; &#xAD; &#xAD; &#xAD; &#xAD; &#xAD; &#xAD; &#xAD; &#xAD; &#xAD; &#xAD; &#xAD; &#xAD; &#xAD; &#xAD; &#xAD; &#xAD; &#xAD; &#xAD; &#xAD; &#xAD; &#xAD; &#xAD; &#xAD; &#xAD; &#xAD; &#xAD; &#xAD; &#xAD; &#xAD; &#xAD; &#xAD; &#xAD; &#xAD; &#xAD; &#xAD; &#xAD; &#xAD; &#xAD; &#xAD; &#xAD; &#xAD; &#xAD; &#xAD; &#xAD; &#xAD; &#xAD; &#xAD; &#xAD; &#xAD; &#xAD; &#xAD; &#xAD; &#xAD; &#xAD; &#xAD; &#xAD; &#xAD; &#xAD; &#xAD; &#xAD; &#xAD; &#xAD; &#xAD; &#xAD; &#xAD; &#xAD; &#xAD; &#xAD; &#xAD; &#xAD; &#xAD; &#xAD; &#xAD; &#xAD; &#xAD; &#xAD; &#xAD; &#xAD; &#xAD; &#xAD; &#xAD; &#xAD; &#xAD; &#xAD; &#xAD; &#xAD; &#xAD; &#xAD; &#xAD;  &#xA0;\r\n        </div>\r\n\r\n        <!-- HEADER WITH FULL-WIDTH BACKGROUND -->\r\n            <table role=\"presentation\" border=\"0\" cellpadding=\"0\" cellspacing=\"0\" class=\"header\" width=\"100%\" style=\"mso-table-lspace: 0pt; mso-table-rspace: 0pt; line-height: 1.4; background-color: #ffffff; width: 100%; border-spacing: 0; border-collapse: collapse;\" bgcolor=\"#ffffff\">\r\n                <!-- Outlook doesn't respect max-width so we need an extra centered table -->\r\n                <!--[if mso]>\r\n                <tr>\r\n                    <td>\r\n                        <center>\r\n                            <table border=\"0\" cellpadding=\"0\" cellspacing=\"0\" width=\"600\">\r\n                <![endif]-->\r\n                <tr>\r\n                    <td style=\"font-family: -apple-system, BlinkMacSystemFont, Roboto, Helvetica, Arial, sans-serif; font-size: 18px; vertical-align: top; color: #15212A;\" valign=\"top\">&#xA0;</td>\r\n                    <td class=\"container\" align=\"center\" style=\"font-family: -apple-system, BlinkMacSystemFont, Roboto, Helvetica, Arial, sans-serif; font-size: 18px; vertical-align: top; color: #15212A;\" valign=\"top\">\r\n                        <div class=\"content\" style=\"box-sizing: border-box; display: block; margin: 0 auto; max-width: 600px;\">\r\n                        <!-- Header content constrained to 600px -->\r\n                        <table role=\"presentation\" border=\"0\" cellpadding=\"0\" cellspacing=\"0\" class=\"header-main\" style=\"border-collapse: separate; mso-table-lspace: 0pt; mso-table-rspace: 0pt; border-spacing: 20px 0; width: 100%; max-width: 600px; background: #ffffff; background-color: transparent;\" width=\"100%\" bgcolor=\"transparent\">\r\n                            <tr>\r\n                                <td class=\"header-content\" style=\"font-family: -apple-system, BlinkMacSystemFont, Roboto, Helvetica, Arial, sans-serif; font-size: 18px; vertical-align: top; color: #15212A; padding: 0; margin: 0 auto;\" valign=\"top\">\r\n                                    <table role=\"presentation\" border=\"0\" cellpadding=\"0\" cellspacing=\"0\" width=\"100%\" style=\"border-collapse: separate; mso-table-lspace: 0pt; mso-table-rspace: 0pt; width: 100%;\">\r\n\r\n                                            <tr class=\"site-info-row\">\r\n                                                <td class=\"site-info\" width=\"100%\" align=\"center\" style=\"font-family: -apple-system, BlinkMacSystemFont, Roboto, Helvetica, Arial, sans-serif; font-size: 18px; vertical-align: top; color: #15212A; padding-top: 32px;\" valign=\"top\">\r\n                                                    <table role=\"presentation\" border=\"0\" cellpadding=\"0\" cellspacing=\"0\" style=\"border-collapse: separate; mso-table-lspace: 0pt; mso-table-rspace: 0pt; width: 100%;\" width=\"100%\">\r\n                                                            <tr>\r\n                                                                <td class=\"site-icon\" style=\"font-family: -apple-system, BlinkMacSystemFont, Roboto, Helvetica, Arial, sans-serif; font-size: 18px; vertical-align: top; color: #15212A; padding-bottom: 8px; padding-top: 8px; text-align: center; border-radius: 3px;\" valign=\"top\" align=\"center\"><a href=\"https://news.aikoreacommunity.com/r/2c53d606?m=9823a680-7a06-429b-8908-3cbd4bf03e7d\" style=\"color: #45e600; text-decoration: none; overflow-wrap: anywhere;\" target=\"_blank\"><img src=\"https://storage.ghost.io/c/e1/33/e133371d-f862-4a59-b7a9-037bf2e0322c/content/images/2023/04/AI-----------PNG.png\" alt=\"AI &#xCF54;&#xB9AC;&#xC544; &#xCEE4;&#xBBA4;&#xB2C8;&#xD2F0; &#xB274;&#xC2A4;&#xB808;&#xD130;\" border=\"0\" width=\"44\" height=\"44\" style=\"border: none; -ms-interpolation-mode: bicubic; max-width: 100%; width: 44px; height: 44px; border-radius: 3px;\"></a></td>\r\n                                                            </tr>\r\n                                                            <tr>\r\n                                                                <td class=\"site-url site-url-bottom-padding\" style=\"font-family: -apple-system, BlinkMacSystemFont, Roboto, Helvetica, Arial, sans-serif; vertical-align: top; color: #15212A; font-size: 16px; letter-spacing: -0.1px; font-weight: 700; text-transform: uppercase; text-align: center; padding-bottom: 12px;\" valign=\"top\" align=\"center\"><div style=\"width: 100% !important;\"><a href=\"https://news.aikoreacommunity.com/r/8a09501d?m=9823a680-7a06-429b-8908-3cbd4bf03e7d\" class=\"site-title\" style=\"text-decoration: none; color: #15212A; overflow-wrap: anywhere;\" target=\"_blank\">AI &#xCF54;&#xB9AC;&#xC544; &#xCEE4;&#xBBA4;&#xB2C8;&#xD2F0; &#xB274;&#xC2A4;&#xB808;&#xD130;</a></div></td>\r\n                                                            </tr>\r\n\r\n                                                    </table>\r\n                                                </td>\r\n                                            </tr>\r\n\r\n                                            <tr>\r\n                                                <td class=\"post-title post-title-no-excerpt\" style=\"font-family: -apple-system, BlinkMacSystemFont, Roboto, Helvetica, Arial, sans-serif; font-size: 18px; vertical-align: top; text-align: center; color: #000000; padding-bottom: 16px;\" valign=\"top\" align=\"center\">\r\n                                                    <table role=\"presentation\" border=\"0\" cellpadding=\"0\" cellspacing=\"0\" style=\"border-collapse: separate; mso-table-lspace: 0pt; mso-table-rspace: 0pt; width: 100%;\" width=\"100%\">\r\n                                                        <tr>\r\n                                                            <td style=\"font-family: -apple-system, BlinkMacSystemFont, Roboto, Helvetica, Arial, sans-serif; vertical-align: top; font-size: 36px; line-height: 1.1; font-weight: 700; text-align: center; color: #000000;\" valign=\"top\" align=\"center\">\r\n                                                                <a href=\"https://news.aikoreacommunity.com/r/95c73189?m=9823a680-7a06-429b-8908-3cbd4bf03e7d\" class=\"post-title-link\" style=\"text-decoration: none; display: block; margin-top: 32px; text-align: center; line-height: 1.1; overflow-wrap: anywhere; color: #000000;\" target=\"_blank\">AI&#xB97C; &#xC4F0;&#xB294; &#xD68C;&#xC0AC;&#39;&#xB294; &#xB05D;&#xB0AC;&#xB2E4;. &#xC774;&#xC81C; &#39;AI&#xB85C; &#xB3CC;&#xC544;&#xAC00;&#xB294; &#xD68C;&#xC0AC;&#39;&#xC758; &#xC2DC;&#xB300;</a>\r\n                                                            </td>\r\n                                                        </tr>\r\n                                                    </table>\r\n                                                </td>\r\n                                            </tr>\r\n                                            <tr>\r\n                                                <td width=\"100%\" style=\"font-family: -apple-system, BlinkMacSystemFont, Roboto, Helvetica, Arial, sans-serif; font-size: 18px; vertical-align: top; color: #15212A; width: 100%;\" align=\"center\" valign=\"top\">\r\n                                                    <table class=\"post-meta-wrapper\" role=\"presentation\" border=\"0\" cellpadding=\"0\" cellspacing=\"0\" width=\"100%\" style=\"border-collapse: separate; mso-table-lspace: 0pt; mso-table-rspace: 0pt; width: 100%; padding-bottom: 32px;\">\r\n                                                        <tr>\r\n                                                            <td height=\"20\" class=\"post-meta post-meta-center\" style=\"font-family: -apple-system, BlinkMacSystemFont, Roboto, Helvetica, Arial, sans-serif; vertical-align: top; color: #15212a; color: rgba(0, 0, 0, 0.6); font-size: 13px; font-weight: 400; text-align: center; padding: 0;\" valign=\"top\" align=\"center\">\r\n                                                                By Bopyo Park &#x2022; <span class=\"post-meta-date\" style=\"white-space: nowrap;\">29 Apr 2026 </span>\r\n                                                            </td>\r\n                                                            <td class=\"post-meta post-meta-center view-online desktop\" style=\"font-family: -apple-system, BlinkMacSystemFont, Roboto, Helvetica, Arial, sans-serif; vertical-align: top; color: rgba(0, 0, 0, 0.6); font-size: 13px; font-weight: 400; text-align: center; display: none;\" valign=\"top\" align=\"center\">\r\n                                                                <a href=\"https://news.aikoreacommunity.com/r/fb4217cf?m=9823a680-7a06-429b-8908-3cbd4bf03e7d\" class=\"view-online-link\" style=\"word-wrap: none; white-space: nowrap; color: #15212a; color: rgba(0, 0, 0, 0.6); overflow-wrap: anywhere; text-decoration: underline;\" target=\"_blank\">View in browser</a>\r\n                                                            </td>\r\n                                                        </tr>\r\n                                                        <tr class=\"post-meta post-meta-center view-online-mobile\" style=\"color: #15212a; color: rgba(0, 0, 0, 0.6); font-size: 13px; font-weight: 400; text-align: center;\" align=\"center\">\r\n                                                            <td height=\"20\" class=\"view-online\" style=\"font-family: -apple-system, BlinkMacSystemFont, Roboto, Helvetica, Arial, sans-serif; vertical-align: top; color: #15212a; color: rgba(0, 0, 0, 0.6); font-size: 13px; font-weight: 400; text-align: center; text-decoration: underline;\" valign=\"top\" align=\"center\">\r\n                                                                <a href=\"https://news.aikoreacommunity.com/r/ca292646?m=9823a680-7a06-429b-8908-3cbd4bf03e7d\" class=\"view-online-link\" style=\"word-wrap: none; white-space: nowrap; color: #15212a; color: rgba(0, 0, 0, 0.6); overflow-wrap: anywhere; text-decoration: underline;\" target=\"_blank\">View in browser</a>\r\n                                                            </td>\r\n                                                        </tr>\r\n                                                    </table>\r\n                                                </td>\r\n                                            </tr>\r\n\r\n                                            <tr class=\"feature-image-row\">\r\n                                                <td class=\"feature-image\r\n                                                \" align=\"center\" style=\"font-family: -apple-system, BlinkMacSystemFont, Roboto, Helvetica, Arial, sans-serif; font-size: 18px; vertical-align: top; color: #15212A; padding-bottom: 30px; width: 100%; text-align: center;\" width=\"100%\" valign=\"top\"><img src=\"https://storage.ghost.io/c/e1/33/e133371d-f862-4a59-b7a9-037bf2e0322c/content/images/size/w1200/2026/04/AI--------------------------------------AI---------------------------------.png\" width=\"600\" style=\"border: none; -ms-interpolation-mode: bicubic; max-width: 100%;\"></td>\r\n                                            </tr>\r\n\r\n                                    </table>\r\n                                </td>\r\n                            </tr>\r\n                        </table>\r\n                        </div>\r\n                    </td>\r\n                    <td style=\"font-family: -apple-system, BlinkMacSystemFont, Roboto, Helvetica, Arial, sans-serif; font-size: 18px; vertical-align: top; color: #15212A;\" valign=\"top\">&#xA0;</td>\r\n                </tr>\r\n                <!--[if mso]>\r\n                            </table>\r\n                        </center>\r\n                    </td>\r\n                </tr>\r\n                <![endif]-->\r\n            </table>\r\n\r\n        <!-- MAIN CONTENT AREA -->\r\n        <table role=\"presentation\" border=\"0\" cellpadding=\"0\" cellspacing=\"0\" class=\"body\" width=\"100%\" style=\"border-collapse: separate; mso-table-lspace: 0pt; mso-table-rspace: 0pt; width: 100%; line-height: 1.4; background-color: #ffffff;\" bgcolor=\"#ffffff\">\r\n            <!-- Outlook doesn't respect max-width so we need an extra centered table -->\r\n            <!--[if mso]>\r\n            <tr>\r\n                <td>\r\n                    <center>\r\n                        <table border=\"0\" cellpadding=\"0\" cellspacing=\"0\" width=\"600\">\r\n            <![endif]-->\r\n            <tr>\r\n                <td style=\"font-family: -apple-system, BlinkMacSystemFont, Roboto, Helvetica, Arial, sans-serif; font-size: 18px; vertical-align: top; color: #15212A;\" valign=\"top\">&#xA0;</td>\r\n                <td class=\"container\" style=\"font-family: -apple-system, BlinkMacSystemFont, Roboto, Helvetica, Arial, sans-serif; font-size: 18px; vertical-align: top; color: #15212A; display: block; max-width: 600px; margin: 0 auto;\" valign=\"top\">\r\n                    <div class=\"content\" style=\"box-sizing: border-box; display: block; margin: 0 auto; max-width: 600px;\">\r\n                        <table role=\"presentation\" border=\"0\" cellpadding=\"0\" cellspacing=\"0\" class=\"main\" width=\"100%\" style=\"border-collapse: separate; mso-table-lspace: 0pt; mso-table-rspace: 0pt; border-spacing: 20px 0; width: 100%; max-width: 600px; background: #ffffff; background-color: #ffffff;\" bgcolor=\"#ffffff\">                            <tr>\r\n                                <td class=\"wrapper\" style=\"font-family: -apple-system, BlinkMacSystemFont, Roboto, Helvetica, Arial, sans-serif; font-size: 18px; vertical-align: top; color: #15212A; box-sizing: border-box;\" valign=\"top\">\r\n                                    <table role=\"presentation\" border=\"0\" cellpadding=\"0\" cellspacing=\"0\" width=\"100%\" data-testid=\"email-preview-content\" style=\"border-collapse: separate; mso-table-lspace: 0pt; mso-table-rspace: 0pt; width: 100%;\">\r\n                                        <tr class=\"post-content-row\">\r\n                                            <td class=\"post-content-sans-serif\" style=\"font-family: -apple-system, BlinkMacSystemFont, Roboto, Helvetica, Arial, sans-serif; vertical-align: top; font-size: 17px; line-height: 1.5; color: #15212A; padding-bottom: 20px; border-bottom: 1px solid #e0e7eb; max-width: 600px;\" valign=\"top\">\r\n                                                <!-- POST CONTENT START -->\r\n                                                <p style=\"margin: 0 0 1.5em 0; line-height: 1.6; color: #15212A;\">&#xC5D0;&#xCF54; &#xBA64;&#xBC84;&#xB2D8;&#xB4E4;,</p><p style=\"margin: 0 0 1.5em 0; line-height: 1.6; color: #15212A;\">&#xC798; &#xC9C0;&#xB0B4;&#xACE0; &#xACC4;&#xC2E0;&#xAC00;&#xC694;? &#xC624;&#xB298;&#xB3C4; &#xCD5C;&#xADFC; AI &#xAD00;&#xB828; &#xC18C;&#xC2DD; &#xC911;&#xC5D0;&#xC11C; &#xD568;&#xAED8; &#xAE4A;&#xC774; &#xC0DD;&#xAC01;&#xD574;&#xBCFC;&#xB9CC;&#xD55C; &#xB0B4;&#xC6A9;&#xC744; &#xB4E4;&#xACE0;&#xC654;&#xC2B5;&#xB2C8;&#xB2E4;. &#xC2E4;&#xB9AC;&#xCF58;&#xBC38;&#xB9AC;&#xC758; &#xAC00;&#xC7A5; &#xC601;&#xD5A5;&#xB825; &#xC788;&#xB294; &#xC561;&#xC140;&#xB7EC;&#xB808;&#xC774;&#xD130;&#xC778; Y Combinator&#xC758; &#xD30C;&#xD2B8;&#xB108; Diana&#xAC00; &#xCD5C;&#xADFC; &#39;How To Build A Company With AI From The Ground Up(AI&#xB85C; &#xD68C;&#xC0AC;&#xB97C; &#xCC98;&#xC74C;&#xBD80;&#xD130; &#xB2E4;&#xC2DC; &#xC9D3;&#xB294; &#xBC95;)&#39;&#xC774;&#xB77C;&#xB294; &#xC8FC;&#xC81C;&#xB85C; &#xC778;&#xC0AC;&#xC774;&#xD2B8;&#xB97C; &#xACF5;&#xC720;&#xD588;&#xB294;&#xB370;&#xC694;. &#xB2E8;&#xC21C;&#xD788; &#39;AI&#xB97C; &#xC5B4;&#xB5BB;&#xAC8C; &#xC798; &#xC4F8;&#xAE4C;?&#39;&#xB97C; &#xB118;&#xC5B4;&#xC11C;, &#39;&#xD68C;&#xC0AC;&#xB77C;&#xB294; &#xC870;&#xC9C1; &#xC790;&#xCCB4;&#xB97C; AI &#xC704;&#xC5D0; &#xC5B4;&#xB5BB;&#xAC8C; &#xC0C8;&#xB85C; &#xC9C0;&#xC5B4;&#xC57C; &#xD558;&#xB294;&#xAC00;?&#39;&#xC5D0; &#xB300;&#xD55C; &#xAD49;&#xC7A5;&#xD788; &#xBCF8;&#xC9C8;&#xC801;&#xC778; &#xD1B5;&#xCC30;&#xC774; &#xB2F4;&#xACA8;&#xC788;&#xC5B4; &#xC5D0;&#xCF54; &#xB274;&#xC2A4;&#xB808;&#xD130; &#xAD6C;&#xB3C5;&#xC790;&#xB2D8;&#xB4E4;&#xACFC; &#xD568;&#xAED8; &#xB098;&#xB220;&#xBCF4;&#xACE0;&#xC790; &#xD569;&#xB2C8;&#xB2E4;.</p><p style=\"margin: 0 0 1.5em 0; line-height: 1.6; color: #15212A;\">&#xC9C0;&#xAE08; &#xC6B0;&#xB9AC;&#xB294; &#xC0B0;&#xC5C5;&#xD601;&#xBA85; &#xC774;&#xD6C4; &#xAC00;&#xC7A5; &#xD070; &#xC870;&#xC9C1; &#xC6B4;&#xC601;&#xC758; &#xD328;&#xB7EC;&#xB2E4;&#xC784; &#xC804;&#xD658;&#xAE30;&#xB97C; &#xC0B4;&#xACE0; &#xC788;&#xC2B5;&#xB2C8;&#xB2E4;. &#xD765;&#xBBF8;&#xB85C;&#xC6B4; &#xC810;&#xC740;, &#xC774; &#xBCC0;&#xD654;&#xAC00; &#xB2E8;&#xC21C;&#xD788; &#39;&#xC5D4;&#xC9C0;&#xB2C8;&#xC5B4;&#xAC00; &#xCF54;&#xB4DC;&#xB97C; &#xB354; &#xBE68;&#xB9AC; &#xC9E0;&#xB2E4;&#39;&#xAC70;&#xB098; &#39;&#xB9C8;&#xCF00;&#xD130;&#xAC00; &#xCE74;&#xD53C;&#xB97C; &#xB354; &#xBE68;&#xB9AC; &#xC4F4;&#xB2E4;&#39;&#xB294; &#xC218;&#xC900;&#xC758; &#xC0DD;&#xC0B0;&#xC131; &#xD5A5;&#xC0C1;&#xC774; &#xC544;&#xB2C8;&#xB77C;&#xB294; &#xC0AC;&#xC2E4;&#xC785;&#xB2C8;&#xB2E4;. Diana&#xC758; &#xD45C;&#xD604;&#xC744; &#xBE4C;&#xB9AC;&#xBA74;, &#xC6B0;&#xB9AC;&#xAC00; &#xC9C0;&#xAE08; &#xBAA9;&#xB3C4;&#xD558;&#xACE0; &#xC788;&#xB294; &#xAC83;&#xC740; &#39;&#xC0DD;&#xC0B0;&#xC131;&#xC758; &#xD5A5;&#xC0C1;&#39;&#xC774; &#xC544;&#xB2C8;&#xB77C; &#39;&#xC644;&#xC804;&#xD788; &#xC0C8;&#xB85C;&#xC6B4; &#xB2A5;&#xB825;&#xC758; &#xCD9C;&#xD604;(Entirely new capabilities)&#39;&#xC785;&#xB2C8;&#xB2E4;. &#xD55C; &#xC0AC;&#xB78C;&#xC774;, &#xACFC;&#xAC70;&#xC5D0;&#xB294; &#xD300; &#xC804;&#xCCB4;&#xAC00; &#xB2EC;&#xB824;&#xB4E4;&#xC5B4;&#xB3C4; &#xB9CC;&#xB4E4; &#xC218; &#xC5C6;&#xC5C8;&#xB358; &#xAC83;&#xC744; &#xB9CC;&#xB4E4;&#xC5B4;&#xB0B4;&#xB294; &#xC2DC;&#xB300;. &#xADF8; &#xC2DC;&#xB300;&#xC758; &#xD68C;&#xC0AC;&#xB294; &#xC5B4;&#xB5BB;&#xAC8C; &#xC0DD;&#xACA8;&#xC57C; &#xD560;&#xAE4C;&#xC694;?</p><p style=\"margin: 0 0 1.5em 0; line-height: 1.6; color: #15212A;\">&#xC624;&#xB298;&#xC740; &#39;AI &#xB124;&#xC774;&#xD2F0;&#xBE0C; &#xD68C;&#xC0AC;(AI-native Company)&#39;&#xB77C;&#xB294; &#xC0C8;&#xB85C;&#xC6B4; &#xAC1C;&#xB150;&#xC744; &#xD1B5;&#xD574;, 1&#xC778; &#xCC3D;&#xC5C5;&#xC790;&#xBD80;&#xD130; &#xAE30;&#xC874; &#xC870;&#xC9C1;&#xC758; &#xB9AC;&#xB354;&#xAE4C;&#xC9C0; &#xBAA8;&#xB450;&#xAC00; &#xD55C; &#xBC88;&#xCBE4; &#xAE4A;&#xC774; &#xC0DD;&#xAC01;&#xD574;&#xBD10;&#xC57C; &#xD560; &#xBCF8;&#xC9C8;&#xC801;&#xC778; &#xC9C8;&#xBB38;&#xB4E4;&#xC744; &#xD568;&#xAED8; &#xD480;&#xC5B4;&#xAC00; &#xBCF4;&#xB824; &#xD569;&#xB2C8;&#xB2E4;. &#xC791;&#xC740; &#xD300;&#xC73C;&#xB85C; &#xAC70;&#xB300;&#xD55C; &#xAE30;&#xC5C5;&#xC744; &#xC774;&#xAE30;&#xB294; &#xBC29;&#xBC95;, &#xADF8;&#xB9AC;&#xACE0; &#xC6B0;&#xB9AC;&#xAC00; &#xC77C;&#xD558;&#xB294; &#xBC29;&#xC2DD; &#xC790;&#xCCB4;&#xB97C; &#xC5B4;&#xB5BB;&#xAC8C; &#xC7AC;&#xC124;&#xACC4;&#xD574;&#xC57C; &#xD558;&#xB294;&#xC9C0;&#xC5D0; &#xB300;&#xD55C; &#xC774;&#xC57C;&#xAE30;&#xC785;&#xB2C8;&#xB2E4;.</p><div class=\"kg-card kg-image-card\" style=\"margin: 0 0 1.5em; padding: 0;\"><img src=\"https://storage.ghost.io/c/e1/33/e133371d-f862-4a59-b7a9-037bf2e0322c/content/images/2026/04/image-78.png\" class=\"kg-image\" alt loading=\"lazy\" width=\"600\" height=\"311\" style=\"border: none; -ms-interpolation-mode: bicubic; display: block; margin: 0 auto; height: auto; width: auto; max-width: 100%;\"></div><h3 id=\"1-ai%EB%8A%94-%EB%8F%84%EA%B5%AC%EA%B0%80-%EC%95%84%EB%8B%88%EB%9D%BC-%EC%9A%B4%EC%98%81%EC%B2%B4%EC%A0%9Cos%EB%8B%A4-%ED%9A%8C%EC%82%AC%EB%A5%BC-%EB%8B%A4%EC%8B%9C-%EC%A0%95%EC%9D%98%ED%95%98%EB%8A%94-%EC%B2%AB-%EB%B2%88%EC%A7%B8-%EC%A7%88%EB%AC%B8\" style=\"margin-top: 0; font-family: -apple-system, BlinkMacSystemFont, Roboto, Helvetica, Arial, sans-serif; line-height: 1.11; font-weight: 700; text-rendering: optimizeLegibility; margin: 1.5em 0 0.5em 0; font-size: 26px; color: #15212A;\">1. AI&#xB294; &#39;&#xB3C4;&#xAD6C;&#39;&#xAC00; &#xC544;&#xB2C8;&#xB77C; &#39;&#xC6B4;&#xC601;&#xCCB4;&#xC81C;(OS)&#39;&#xB2E4;: &#xD68C;&#xC0AC;&#xB97C; &#xB2E4;&#xC2DC; &#xC815;&#xC758;&#xD558;&#xB294; &#xCCAB; &#xBC88;&#xC9F8; &#xC9C8;&#xBB38;</h3><p style=\"margin: 0 0 1.5em 0; line-height: 1.6; color: #15212A;\"></p><p style=\"margin: 0 0 1.5em 0; line-height: 1.6; color: #15212A;\">&#xB300;&#xBD80;&#xBD84;&#xC758; &#xAE30;&#xC5C5;&#xC774; AI&#xB97C; &#xBC14;&#xB77C;&#xBCF4;&#xB294; &#xC2DC;&#xAC01;&#xC740; &#xC5EC;&#xC804;&#xD788; &#39;&#xD3B8;&#xB9AC;&#xD55C; &#xB3C4;&#xAD6C;&#39; &#xC218;&#xC900;&#xC5D0; &#xBA38;&#xBB3C;&#xB7EC; &#xC788;&#xC2B5;&#xB2C8;&#xB2E4;. &#xB9C8;&#xCE58; &#xC0C8;&#xB85C;&#xC6B4; &#xC6CC;&#xB4DC;&#xD504;&#xB85C;&#xC138;&#xC11C;&#xB098; &#xB354; &#xC88B;&#xC740; &#xC5D1;&#xC140;&#xC744; &#xB3C4;&#xC785;&#xD558;&#xB4EF;, &quot;&#xAE30;&#xC874; &#xC6CC;&#xD06C;&#xD50C;&#xB85C;&#xC6B0;&#xC5D0; AI &#xCF54;&#xD30C;&#xC77C;&#xB7FF;&#xC744; &#xBD99;&#xC774;&#xACE0; &#xAE30;&#xB2A5;&#xC744; &#xB354; &#xBE68;&#xB9AC; &#xCD9C;&#xC2DC;&#xD558;&#xC790;&quot;&#xB294; &#xC2DD;&#xC758; &#xC811;&#xADFC;&#xC785;&#xB2C8;&#xB2E4;. &#xD558;&#xC9C0;&#xB9CC; Diana&#xB294; &#xC774;&#xB7F0; &#xAD00;&#xC810;&#xC774; &#xC9C0;&#xAE08; &#xC77C;&#xC5B4;&#xB098;&#xACE0; &#xC788;&#xB294; &#xAC70;&#xB300;&#xD55C; &#xBCC0;&#xD654;&#xB97C; &#xC644;&#xC804;&#xD788; &#xB193;&#xCE58;&#xACE0; &#xC788;&#xB2E4;&#xACE0; &#xB2E8;&#xC5B8;&#xD569;&#xB2C8;&#xB2E4;.</p><p style=\"margin: 0 0 1.5em 0; line-height: 1.6; color: #15212A;\">&#xADF8;&#xB140;&#xAC00; &#xC81C;&#xC2DC;&#xD558;&#xB294; &#xD575;&#xC2EC; &#xBA85;&#xC81C;&#xB294; &#xCDA9;&#xACA9;&#xC801;&#xC774;&#xB9AC;&#xB9CC;&#xCE58; &#xB2E8;&#xC21C;&#xD569;&#xB2C8;&#xB2E4;. &quot;AI&#xB294; &#xB2F9;&#xC2E0;&#xC758; &#xD68C;&#xC0AC;&#xAC00; &#39;&#xC0AC;&#xC6A9;&#xD558;&#xB294;&#39; &#xB3C4;&#xAD6C;&#xAC00; &#xC544;&#xB2C8;&#xB77C;, &#xB2F9;&#xC2E0;&#xC758; &#xD68C;&#xC0AC;&#xAC00; &#xADF8; &#xC704;&#xC5D0;&#xC11C; &#39;&#xB3CC;&#xC544;&#xAC00;&#xB294;&#39; &#xC6B4;&#xC601;&#xCCB4;&#xC81C;(Operating System)&#xC5EC;&#xC57C; &#xD55C;&#xB2E4;.&quot;</p><p style=\"margin: 0 0 1.5em 0; line-height: 1.6; color: #15212A;\">&#xC774; &#xBE44;&#xC720;&#xB97C; &#xACF1;&#xC539;&#xC5B4;&#xBCFC; &#xD544;&#xC694;&#xAC00; &#xC788;&#xC2B5;&#xB2C8;&#xB2E4;. &#xC6B0;&#xB9AC;&#xB294; &#xCEF4;&#xD4E8;&#xD130;&#xB97C; &#xC0AC;&#xC6A9;&#xD560; &#xB54C; &#xC708;&#xB3C4;&#xC6B0;&#xB098; macOS&#xB77C;&#xB294; &#xC6B4;&#xC601;&#xCCB4;&#xC81C;&#xB97C; &#39;&#xC0AC;&#xC6A9;&#xD55C;&#xB2E4;&#39;&#xACE0; &#xB9D0;&#xD558;&#xC9C0; &#xC54A;&#xC2B5;&#xB2C8;&#xB2E4;. &#xC6B0;&#xB9AC;&#xC758; &#xBAA8;&#xB4E0; &#xC791;&#xC5C5;&#xC774; &#xADF8; &#xC704;&#xC5D0;&#xC11C; &#xC790;&#xC5F0;&#xC2A4;&#xB7FD;&#xAC8C; &#xD758;&#xB7EC;&#xAC08; &#xBFD0;&#xC785;&#xB2C8;&#xB2E4;. &#xC6B4;&#xC601;&#xCCB4;&#xC81C;&#xB294; &#xC758;&#xC2DD;&#xD558;&#xC9C0; &#xC54A;&#xC544;&#xB3C4; &#xBAA8;&#xB4E0; &#xAC83;&#xC758; &#xAE30;&#xBC18;&#xC774; &#xB418;&#xC5B4; &#xC90D;&#xB2C8;&#xB2E4;. AI &#xB124;&#xC774;&#xD2F0;&#xBE0C; &#xD68C;&#xC0AC;&#xB3C4; &#xB9C8;&#xCC2C;&#xAC00;&#xC9C0;&#xC5EC;&#xC57C; &#xD569;&#xB2C8;&#xB2E4;. &#xBAA8;&#xB4E0; &#xC6CC;&#xD06C;&#xD50C;&#xB85C;&#xC6B0;, &#xBAA8;&#xB4E0; &#xC758;&#xC0AC;&#xACB0;&#xC815;, &#xBAA8;&#xB4E0; &#xD504;&#xB85C;&#xC138;&#xC2A4;&#xAC00; &#xB04A;&#xC784;&#xC5C6;&#xC774; &#xD559;&#xC2B5;&#xD558;&#xACE0; &#xAC1C;&#xC120;&#xB418;&#xB294; &#39;&#xC9C0;&#xB2A5;&#xC758; &#xCE35;(Intelligent Layer)&#39;&#xC744; &#xAC70;&#xCCD0; &#xD758;&#xB7EC;&#xC57C; &#xD55C;&#xB2E4;&#xB294; &#xAC83;&#xC785;&#xB2C8;&#xB2E4;.</p><p style=\"margin: 0 0 1.5em 0; line-height: 1.6; color: #15212A;\">&#xAE30;&#xC874;&#xC758; &#xD68C;&#xC0AC;&#xB4E4;&#xC740; &#xADF8;&#xB140;&#xC758; &#xD45C;&#xD604;&#xC5D0; &#xB530;&#xB974;&#xBA74; &#39;&#xC624;&#xD508; &#xB8E8;&#xD504;(Open Loop) &#xC2DC;&#xC2A4;&#xD15C;&#39;&#xC73C;&#xB85C; &#xC6B4;&#xC601;&#xB418;&#xC5B4; &#xC654;&#xC2B5;&#xB2C8;&#xB2E4;. &#xC758;&#xC0AC;&#xACB0;&#xC815;&#xC744; &#xB0B4;&#xB9AC;&#xACE0;, &#xC2E4;&#xD589;&#xD558;&#xACE0;, &#xADF8; &#xACB0;&#xACFC;&#xB97C; &#xCE21;&#xC815;&#xD558;&#xC9C0;&#xB9CC;, &#xADF8;&#xAC83;&#xC774; &#xB2E4;&#xC2DC; &#xC2DC;&#xC2A4;&#xD15C;&#xC5D0; &#xCCB4;&#xACC4;&#xC801;&#xC73C;&#xB85C; &#xD53C;&#xB4DC;&#xBC31;&#xB418;&#xC9C0; &#xC54A;&#xB294; &#xAD6C;&#xC870;&#xC785;&#xB2C8;&#xB2E4;. &#xB9C8;&#xCE58; &#xD654;&#xC0B4;&#xC744; &#xC3D8;&#xACE0; &#xC5B4;&#xB514;&#xC5D0; &#xB9DE;&#xC558;&#xB294;&#xC9C0; &#xD655;&#xC778;&#xD558;&#xC9C0; &#xC54A;&#xB294; &#xAD81;&#xC218;&#xC640; &#xAC19;&#xC2B5;&#xB2C8;&#xB2E4;. &#xC774;&#xB7F0; &#xC2DC;&#xC2A4;&#xD15C;&#xC740; &#xBCF8;&#xC9C8;&#xC801;&#xC73C;&#xB85C; &#39;&#xC190;&#xC2E4;(Lossy)&#39;&#xC774; &#xBC1C;&#xC0DD;&#xD560; &#xC218;&#xBC16;&#xC5D0; &#xC5C6;&#xC2B5;&#xB2C8;&#xB2E4;. &#xC815;&#xBCF4;&#xAC00; &#xC0AC;&#xB78C;&#xC5D0;&#xC11C; &#xC0AC;&#xB78C;&#xC73C;&#xB85C;, &#xD68C;&#xC758;&#xC5D0;&#xC11C; &#xD68C;&#xC758;&#xB85C; &#xC62E;&#xACA8;&#xAC00;&#xB294; &#xB3D9;&#xC548; &#xB9C8;&#xCE58; &#xAE68;&#xC9C4; &#xD56D;&#xC544;&#xB9AC;&#xC5D0;&#xC11C; &#xBB3C;&#xC774; &#xC0C8;&#xB4EF; &#xB04A;&#xC784;&#xC5C6;&#xC774; &#xBE60;&#xC838;&#xB098;&#xAC11;&#xB2C8;&#xB2E4;.</p><blockquote style=\"margin: 0; padding: 0; border-left: #45e600 2px solid; font-size: 17px; font-weight: 500; line-height: 1.6; letter-spacing: -0.2px;\"><p style=\"line-height: 1.6; margin: 2em 25px; font-size: 1em; padding: 0; color: #15212A;\"><strong style=\"font-weight: 700;\">&#xC5EC;&#xAE30;&#xC11C;&#xBD80;&#xD130;&#xB294; &#xC720;&#xB8CC; &#xAD6C;&#xB3C5;&#xC790; &#xC804;&#xC6A9;&#xC785;&#xB2C8;&#xB2E4;.</strong></p></blockquote><p style=\"margin: 0 0 1.5em 0; line-height: 1.6; color: #15212A;\">&#xC194;&#xC9C1;&#xD558;&#xAC8C; &#xC5EC;&#xCB59;&#xACA0;&#xC2B5;&#xB2C8;&#xB2E4;. &#xC9C0;&#xB09C; &#xD55C; &#xC8FC;, &#xC0C8;&#xB85C; &#xC3DF;&#xC544;&#xC9C4; AI &#xB274;&#xC2A4; &#xC911; &#xBA87; &#xAC1C;&#xB098; &#xB05D;&#xAE4C;&#xC9C0; &#xC77D;&#xC73C;&#xC168;&#xB098;&#xC694;?</p><p style=\"margin: 0 0 1.5em 0; line-height: 1.6; color: #15212A;\">&#xB808;&#xB2C8;&#xC2A4; &#xD31F;&#xCE90;&#xC2A4;&#xD2B8;, &#xC0AC;&#xC774;&#xBA3C; &#xC70C;&#xB9AC;&#xC2A8;&#xC758; &#xBE14;&#xB85C;&#xADF8;, &#xC564;&#xD2B8;&#xB85C;&#xD53D; &#xC2DC;&#xC2A4;&#xD15C; &#xCE74;&#xB4DC;, &#xB9E4;&#xC77C; &#xC62C;&#xB77C;&#xC624;&#xB294; &#xC601;&#xBB38; &#xC544;&#xD2F0;&#xD074;&#xB4E4;. &#xB2E4; &#xCC59;&#xACA8;&#xBCF4;&#xACE0; &#xC2F6;&#xC9C0;&#xB9CC; &#xD604;&#xC2E4;&#xC740; &#xD0ED;&#xB9CC; 30&#xAC1C; &#xC5F4;&#xC5B4;&#xB193;&#xACE0; &#xC7A0;&#xB4DC;&#xB294; &#xB0A0;&#xC774; &#xB354; &#xB9CE;&#xC8E0;. &#xC800;&#xB3C4; &#xADF8;&#xB7AC;&#xC2B5;&#xB2C8;&#xB2E4;. &#xADF8;&#xB798;&#xC11C; &#xC774; &#xC77C;&#xC744; &#xC9C1;&#xC5C5;&#xC73C;&#xB85C; &#xC0BC;&#xAE30;&#xB85C; &#xD588;&#xC2B5;&#xB2C8;&#xB2E4;.</p><p style=\"margin: 0 0 1.5em 0; line-height: 1.6; color: #15212A;\"><strong style=\"font-weight: 700;\">&#xC5D0;&#xCF54; &#xB274;&#xC2A4;&#xB808;&#xD130;&#xAC00; &#xD558;&#xB294; &#xC77C;&#xC740; &#xB2E8;&#xC21C;&#xD569;&#xB2C8;&#xB2E4;.</strong> &#xD574;&#xC678; &#xD1B1;&#xD2F0;&#xC5B4; AI &#xD06C;&#xB9AC;&#xC5D0;&#xC774;&#xD130;&#xB4E4;&#xC758; &#xCF58;&#xD150;&#xCE20;&#xB97C; &#xB9E4;&#xC77C; &#xCD94;&#xC801;&#xD558;&#xACE0;, &#xD55C;&#xAD6D;&#xC5D0;&#xC11C; &#xC77C;&#xD558;&#xB294; &#xC6B0;&#xB9AC;&#xC5D0;&#xAC8C; &#xC9C4;&#xC9DC; &#xD544;&#xC694;&#xD55C; &#xC778;&#xC0AC;&#xC774;&#xD2B8;&#xB9CC; &#xACE8;&#xB77C;, &#xD55C; &#xD1B5;&#xC758; &#xC774;&#xBA54;&#xC77C;&#xB85C; &#xC815;&#xB9AC;&#xD574; &#xB4DC;&#xB9BD;&#xB2C8;&#xB2E4;. &#xC5EC;&#xB7EC;&#xBD84;&#xC774; 30&#xAC1C;&#xC758; &#xD0ED;&#xC744; &#xC5EC;&#xB294; &#xB300;&#xC2E0;, &#xC800; &#xD55C; &#xC0AC;&#xB78C;&#xC774; 300&#xAC1C;&#xB97C; &#xC5FD;&#xB2C8;&#xB2E4;.</p><p style=\"margin: 0 0 1.5em 0; line-height: 1.6; color: #15212A;\"><strong style=\"font-weight: 700;\">&#xC720;&#xB8CC; &#xBA64;&#xBC84;&#xC2ED;&#xC5D0;&#xB294; &#xC138; &#xAC00;&#xC9C0;&#xAC00; &#xD3EC;&#xD568;&#xB429;&#xB2C8;&#xB2E4;.</strong></p><p style=\"margin: 0 0 1.5em 0; line-height: 1.6; color: #15212A;\">&#xCCAB;&#xC9F8;, <strong style=\"font-weight: 700;\">&#xBAA8;&#xB4E0; &#xC2EC;&#xCE35; &#xBD84;&#xC11D; &#xC544;&#xD2F0;&#xD074;&#xC758; &#xC804;&#xBB38; &#xC5F4;&#xB78C;&#xAD8C;.</strong> &#xBB34;&#xB8CC; &#xAD6C;&#xB3C5;&#xC790;&#xC5D0;&#xAC8C;&#xB294; &#xC808;&#xBC18;&#xB9CC; &#xACF5;&#xAC1C;&#xB418;&#xB294; &#xD575;&#xC2EC; &#xC778;&#xC0AC;&#xC774;&#xD2B8;&#xB97C; &#xB05D;&#xAE4C;&#xC9C0; &#xC77D;&#xC73C;&#xC2E4; &#xC218; &#xC788;&#xC2B5;&#xB2C8;&#xB2E4;.</p><p style=\"margin: 0 0 1.5em 0; line-height: 1.6; color: #15212A;\">&#xB458;&#xC9F8;, <strong style=\"font-weight: 700;\">&#xC81C;&#xAC00; &#xC9C1;&#xC811; &#xB179;&#xC74C;&#xD55C; &#xC624;&#xB514;&#xC624; &#xB808;&#xD130;.</strong> &#xCD9C;&#xADFC;&#xAE38; &#xC9C0;&#xD558;&#xCCA0;&#xC5D0;&#xC11C;, &#xB7EC;&#xB2DD;&#xBA38;&#xC2E0; &#xC704;&#xC5D0;&#xC11C;, &#xC124;&#xAC70;&#xC9C0;&#xD558;&#xBA74;&#xC11C;. &#xB208;&#xC774; &#xC790;&#xC720;&#xB86D;&#xC9C0; &#xBABB;&#xD55C; &#xC2DC;&#xAC04;&#xC744; &#xD559;&#xC2B5; &#xC2DC;&#xAC04;&#xC73C;&#xB85C; &#xBC14;&#xAFD4;&#xB4DC;&#xB9BD;&#xB2C8;&#xB2E4;.</p><p style=\"margin: 0 0 1.5em 0; line-height: 1.6; color: #15212A;\">&#xC14B;&#xC9F8;, <strong style=\"font-weight: 700;\">&#xC6D0;&#xBCF8; &#xC601;&#xC0C1;&#xC758; &#xD480; &#xC790;&#xB9C9; SRT &#xD30C;&#xC77C;.</strong> &#xCC57;GPT, &#xD074;&#xB85C;&#xB4DC;, &#xC81C;&#xBBF8;&#xB098;&#xC774;&#xC5D0; &#xADF8;&#xB300;&#xB85C; &#xB123;&#xC5B4; &#xC5EC;&#xB7EC;&#xBD84;&#xB9CC;&#xC758; &#xD559;&#xC2B5; &#xC790;&#xB8CC;, &#xC694;&#xC57D;&#xBCF8;, Q&amp;A &#xB370;&#xC774;&#xD130;&#xB85C; &#xAC00;&#xACF5;&#xD558;&#xC2E4; &#xC218; &#xC788;&#xC2B5;&#xB2C8;&#xB2E4;. &#xC774;&#xAC74; &#xB2E4;&#xB978; &#xC5B4;&#xB5A4; &#xD55C;&#xAD6D; &#xB274;&#xC2A4;&#xB808;&#xD130;&#xC5D0;&#xC11C;&#xB3C4; &#xC81C;&#xACF5;&#xD558;&#xC9C0; &#xC54A;&#xB294; &#xC790;&#xC0B0;&#xC785;&#xB2C8;&#xB2E4;.</p><div class=\"kg-card kg-image-card\" style=\"margin: 0 0 1.5em; padding: 0;\"><img src=\"https://storage.ghost.io/c/e1/33/e133371d-f862-4a59-b7a9-037bf2e0322c/content/images/2026/04/image-41.png\" class=\"kg-image\" alt loading=\"lazy\" width=\"443\" height=\"466\" style=\"border: none; -ms-interpolation-mode: bicubic; display: block; margin: 0 auto; height: auto; width: auto; max-width: 100%;\"></div><p style=\"margin: 0 0 1.5em 0; line-height: 1.6; color: #15212A;\">&#x1F449;<a href=\"https://news.aikoreacommunity.com/r/8aafcb2d?m=9823a680-7a06-429b-8908-3cbd4bf03e7d\" rel=\"noreferrer\" style=\"overflow-wrap: anywhere; color: #45e600; text-decoration: underline;\" target=\"_blank\">&#xD55C;&#xB2EC;&#xC5D0; 5.19$ &#xD22C;&#xC790;&#xD558;&#xC154;&#xC11C; &#xD3B8;&#xC548;&#xD558;&#xAC8C; AI &#xC778;&#xC0AC;&#xC774;&#xD2B8; &#xD761;&#xC218;&#xD558;&#xC138;&#xC694;.</a></p><p style=\"margin: 0 0 1.5em 0; line-height: 1.6; color: #15212A;\"><strong style=\"font-weight: 700;\">&#xC6D4; $5.19.</strong> &#xC2A4;&#xD0C0;&#xBC85;&#xC2A4; &#xC544;&#xBA54;&#xB9AC;&#xCE74;&#xB178; &#xD55C; &#xC794;&#xBCF4;&#xB2E4; &#xC309;&#xB2C8;&#xB2E4;. &#xADF8;&#xB9AC;&#xACE0; &#xADF8; &#xD55C; &#xC794;&#xC758; &#xAC12;&#xC73C;&#xB85C;, &#xC5EC;&#xB7EC;&#xBD84;&#xC740; &#xB9E4;&#xC8FC; &#xD3C9;&#xADE0; 5&#xC2DC;&#xAC04;&#xC758; &#xB9AC;&#xC11C;&#xCE58; &#xC2DC;&#xAC04;&#xC744; &#xB3CC;&#xB824;&#xBC1B;&#xAC8C; &#xB429;&#xB2C8;&#xB2E4;.</p><p style=\"margin: 0 0 1.5em 0; line-height: 1.6; color: #15212A;\">&#xB2E4;&#xB9CC; &#xD55C; &#xAC00;&#xC9C0; &#xC591;&#xD574; &#xBD80;&#xD0C1;&#xB4DC;&#xB9BD;&#xB2C8;&#xB2E4;. &#xCF58;&#xD150;&#xCE20; &#xD488;&#xC9C8;&#xC744; &#xC9C0;&#xD0A4;&#xAE30; &#xC704;&#xD574; &#xBA64;&#xBC84; &#xC218;&#xAC00; &#xC77C;&#xC815; &#xADDC;&#xBAA8;&#xB97C; &#xB118;&#xC73C;&#xBA74; &#xC2E0;&#xADDC; &#xBAA8;&#xC9D1;&#xC744; &#xC7A0;&#xC2DC; &#xBA48;&#xCD9C; &#xC608;&#xC815;&#xC785;&#xB2C8;&#xB2E4;. &#xC9C0;&#xAE08; &#xD569;&#xB958;&#xD558;&#xC2E0; &#xBD84;&#xB4E4;&#xAED8;&#xB294; &#xD5A5;&#xD6C4; &#xAC00;&#xACA9;&#xC774; &#xC778;&#xC0C1;&#xB418;&#xB354;&#xB77C;&#xB3C4; <strong style=\"font-weight: 700;\">&#xD604;&#xC7AC; &#xAC00;&#xACA9;&#xC774; &#xD3C9;&#xC0DD; &#xC720;&#xC9C0;</strong>&#xB429;&#xB2C8;&#xB2E4;.</p><p style=\"margin: 0 0 1.5em 0; line-height: 1.6; color: #15212A;\"><strong style=\"font-weight: 700;\">&#xC9C0;&#xAE08; &#xD569;&#xB958;&#xD558;&#xC2DC;&#xBA74; &#xBC1B;&#xAC8C; &#xB418;&#xB294; &#xAC83;:</strong></p><ul style=\"margin: 0 0 1.5em 0; line-height: 1.6; padding-left: 1.3em; padding-right: 1.5em; list-style: disc; max-width: 100%;\"><li style=\"margin: 0.5em 0; padding-left: 0.3em; line-height: 1.6; color: #15212A;\">&#xB9E4;&#xC8FC; &#xD050;&#xB808;&#xC774;&#xC158;&#xB41C; &#xAE00;&#xB85C;&#xBC8C; AI &#xC2EC;&#xCE35; &#xBD84;&#xC11D; (&#xC804;&#xBB38;)</li><li style=\"margin: 0.5em 0; padding-left: 0.3em; line-height: 1.6; color: #15212A;\">&#xC6B4;&#xC804;&#xB7;&#xC6B4;&#xB3D9;&#xB7;&#xC9D1;&#xC548;&#xC77C; &#xC2DC;&#xAC04;&#xC744; &#xD559;&#xC2B5; &#xC2DC;&#xAC04;&#xC73C;&#xB85C; &#xBC14;&#xAFD4;&#xC8FC;&#xB294; &#xC624;&#xB514;&#xC624; &#xB808;&#xD130;</li><li style=\"margin: 0.5em 0; padding-left: 0.3em; line-height: 1.6; color: #15212A;\">AI&#xC5D0;&#xAC8C; &#xC9C1;&#xC811; &#xD559;&#xC2B5;&#xC2DC;&#xD0AC; &#xC218; &#xC788;&#xB294; &#xC6D0;&#xBCF8; SRT &#xC790;&#xB9C9; &#xD30C;&#xC77C;</li><li style=\"margin: 0.5em 0; padding-left: 0.3em; line-height: 1.6; color: #15212A;\">&#xACFC;&#xAC70; &#xBC1C;&#xD589;&#xBD84; &#xC804;&#xCCB4; &#xC544;&#xCE74;&#xC774;&#xBE0C; &#xC811;&#xADFC;&#xAD8C;</li></ul><p style=\"margin: 0 0 1.5em 0; line-height: 1.6; color: #15212A;\"><a href=\"https://news.aikoreacommunity.com/r/3fc199b3?m=9823a680-7a06-429b-8908-3cbd4bf03e7d\" rel=\"noreferrer\" style=\"overflow-wrap: anywhere; color: #45e600; text-decoration: underline;\" target=\"_blank\">&#x1F449; <strong style=\"font-weight: 700;\">[&#xC6D4; $5.19&#xB85C; &#xD569;&#xB958;&#xD558;&#xAE30;]</strong></a></p><p style=\"margin: 0 0 1.5em 0; line-height: 1.6; color: #15212A;\">&#xC77D;&#xC744; &#xC2DC;&#xAC04;&#xC774; &#xC5C6;&#xC5B4;&#xC11C;, &#xC815;&#xBCF4;&#xAC00; &#xB108;&#xBB34; &#xB9CE;&#xC544;&#xC11C;, &#xB354; &#xC774;&#xC0C1; &#xB4A4;&#xCC98;&#xC9C0;&#xACE0; &#xC2F6;&#xC9C0; &#xC54A;&#xC544;&#xC11C;. &#xC774;&#xC720;&#xB294; &#xC0AC;&#xB78C;&#xB9C8;&#xB2E4; &#xB2E4;&#xB974;&#xC9C0;&#xB9CC;, &#xACB0;&#xAD6D; &#xD55C; &#xAC00;&#xC9C0;&#xB85C; &#xBAA8;&#xC785;&#xB2C8;&#xB2E4;.</p><p style=\"margin: 0 0 1.5em 0; line-height: 1.6; color: #15212A;\"><strong style=\"font-weight: 700;\">&quot;&#xB0B4; &#xC2DC;&#xAC04;&#xC744; &#xB354; &#xAC00;&#xCE58; &#xC788;&#xAC8C; &#xC4F0;&#xACE0; &#xC2F6;&#xB2E4;.&quot;</strong></p><p style=\"margin: 0 0 1.5em 0; line-height: 1.6; color: #15212A;\">&#xADF8; &#xACB0;&#xC815;&#xC744; &#xC624;&#xB298;, &#xCEE4;&#xD53C; &#xD55C; &#xC794; &#xAC12;&#xC73C;&#xB85C; &#xC2DC;&#xC791;&#xD574; &#xBCF4;&#xC138;&#xC694;.</p>\r\n                                                <!-- POST CONTENT END -->\r\n\r\n                                                    <div class=\"kg-paywall align-center\" style=\"text-align: center;\">\r\n                                                        <table class=\"kg-paywall-hr\" role=\"presentation\" width=\"100%\" border=\"0\" cellpadding=\"0\" cellspacing=\"0\" style=\"border-collapse: separate; mso-table-lspace: 0pt; mso-table-rspace: 0pt; width: 100%;\">\r\n                                                            <tbody>\r\n                                                                <tr>\r\n                                                                    <td style=\"font-family: -apple-system, BlinkMacSystemFont, Roboto, Helvetica, Arial, sans-serif; vertical-align: top; color: #15212A; margin: 0; padding-top: 1.5em; padding-bottom: 3em; font-size: 17px;\" valign=\"top\">\r\n                                                                        <!--[if !mso]><!-- -->\r\n                                                                        <hr style=\"position: relative; width: 100%; margin: 3em 0; padding: 0; height: 1px; background-color: transparent; border: 0; border-top: 1px solid #e0e7eb; display: none;\">\r\n                                                                        <!--<![endif]-->\r\n                                                                        <table class=\"kg-hr\" role=\"presentation\" border=\"0\" cellpadding=\"0\" cellspacing=\"0\" style=\"border-collapse: separate; mso-table-lspace: 0pt; mso-table-rspace: 0pt; width: 100%;\" width=\"100%\">\r\n                                                                            <tbody>\r\n                                                                                <tr>\r\n                                                                                    <td style=\"font-family: -apple-system, BlinkMacSystemFont, Roboto, Helvetica, Arial, sans-serif; vertical-align: top; color: #15212A; padding-top: 1.5em; padding-bottom: 3em; margin: 0; padding: 0; border-top: 1px solid #e0e7eb; font-size: 0; line-height: 0;\" valign=\"top\">&#xA0;</td>\r\n                                                                                </tr>\r\n                                                                            </tbody>\r\n                                                                        </table>\r\n                                                                    </td>\r\n                                                                </tr>\r\n                                                            </tbody>\r\n                                                        </table>\r\n                                                        <h3 style=\"font-family: -apple-system, BlinkMacSystemFont, Roboto, Helvetica, Arial, sans-serif; line-height: 1.11; font-weight: 700; text-rendering: optimizeLegibility; margin: 1.5em 0 0.5em 0; font-size: 26px; margin-top: 0; color: #15212A; text-wrap: pretty;\">Upgrade to continue reading.</h3>\r\n                                                        <p style=\"line-height: 1.6; max-width: 440px; margin: 0 auto 1.5em auto; text-wrap: pretty; color: #15212A;\">Become a paid member of AI &#xCF54;&#xB9AC;&#xC544; &#xCEE4;&#xBBA4;&#xB2C8;&#xD2F0; &#xB274;&#xC2A4;&#xB808;&#xD130; to get access to all premium content.</p>\r\n                                                            <table border=\"0\" cellpadding=\"0\" cellspacing=\"0\" style=\"border-collapse: separate; mso-table-lspace: 0pt; mso-table-rspace: 0pt; width: 100%;\" width=\"100%\">\r\n                                                                <tr>\r\n                                                                    <td style=\"font-family: -apple-system, BlinkMacSystemFont, Roboto, Helvetica, Arial, sans-serif; font-size: 18px; vertical-align: top; color: #15212A;\" valign=\"top\">\r\n                                                                        <table class=\"btn\" border=\"0\" cellspacing=\"0\" cellpadding=\"0\" align=\"center\" style=\"border-collapse: separate; mso-table-lspace: 0pt; mso-table-rspace: 0pt; box-sizing: border-box; width: auto;\" width=\"auto\">\r\n                                                                            <tr>\r\n                                                                                <td align=\"center\" style=\"font-size: 18px; vertical-align: top; color: #15212A; padding: 8px 20px 9px; background-color: #45e600; border-radius: 6px; text-align: center; font-family: -apple-system, BlinkMacSystemFont, Roboto, Helvetica, Arial, sans-serif;\" valign=\"top\" bgcolor=\"#45e600\">\r\n                                                                                    <a href=\"https://news.aikoreacommunity.com/r/74280f9b?m=9823a680-7a06-429b-8908-3cbd4bf03e7d\" style=\"overflow-wrap: anywhere; box-sizing: border-box; color: #FFFFFF; cursor: pointer; display: inline-block; font-size: 15px; font-weight: 600; margin: 0; text-decoration: none;\" target=\"_blank\">Upgrade</a>\r\n                                                                                </td>\r\n                                                                            </tr>\r\n                                                                        </table>\r\n                                                                    </td>\r\n                                                                </tr>\r\n                                                            </table>\r\n                                                        <p style=\"line-height: 1.6; max-width: 440px; margin: 0 auto 1.5em auto; text-wrap: pretty; color: #15212A;\"></p>\r\n                                                    </div>                                            </td>\r\n                                        </tr>\r\n                                    </table>\r\n                                </td>\r\n                            </tr>\r\n\r\n                            <!-- END MAIN CONTENT AREA -->\r\n\r\n                                <tr>\r\n                                    <td class=\"feedback-buttons-container\" dir=\"ltr\" width=\"100%\" align=\"center\" style=\"font-family: -apple-system, BlinkMacSystemFont, Roboto, Helvetica, Arial, sans-serif; font-size: 18px; vertical-align: top; color: #15212A; padding: 32px 0 24px; border-bottom: 1px solid #e0e7eb; text-align: center; background-color: #ffffff;\" valign=\"top\" bgcolor=\"#ffffff\">\r\n                                        <table class=\"feedback-buttons\" role=\"presentation\" border=\"0\" cellpadding=\"0\" cellspacing=\"0\" style=\"border-collapse: separate; mso-table-lspace: 0pt; mso-table-rspace: 0pt; margin: auto; width: 100%;\" width=\"100%\">\r\n                                            <tr>\r\n                                                    <td dir=\"ltr\" valign=\"top\" align=\"center\" style=\"font-size: 18px; color: #15212A; display: inline-block; box-sizing: border-box; vertical-align: top; font-family: inherit; text-align: center; padding: 0 4px 4px; cursor: pointer; width: 33.33%;\" width=\"33.33%\">\r\n                                                        <a href=\"https://news.aikoreacommunity.com/ai-native-company-yc-token-maxing-1000x-engineer/#/feedback/69f1e380602e450001e3325e/1/?uuid=9823a680-7a06-429b-8908-3cbd4bf03e7d&amp;key=3979968e61bafb918ec3c736e13c83f9f3e66de65fa4fd7d1d62e41009bef050\" target=\"_blank\" style=\"color: #45e600; text-decoration: none; overflow-wrap: anywhere;\">\r\n                                                            <img src=\"https://static.ghost.org/v5.0.0/images/more-like-this-mobile.png\" border=\"0\" width=\"42\" height=\"42\" alt=\"More like this\" style=\"border: none; -ms-interpolation-mode: bicubic; max-width: 100%; display: block; margin: 0 auto; vertical-align: middle;\">\r\n                                                            <p class=\"feedback-button-text\" style=\"display: inline-block; font-family: -apple-system, BlinkMacSystemFont, Roboto, Helvetica, Arial, sans-serif; color: #15212A; font-weight: 500; margin: 1em 0 0 0; line-height: 1.4; word-break: break-word; font-size: 13px;\">More like this</p>\r\n                                                        </a>\r\n                                                    </td>\r\n                                                    <td dir=\"ltr\" valign=\"top\" align=\"center\" style=\"font-size: 18px; color: #15212A; display: inline-block; box-sizing: border-box; vertical-align: top; font-family: inherit; text-align: center; padding: 0 4px 4px; cursor: pointer; width: 33.33%;\" width=\"33.33%\">\r\n                                                        <a href=\"https://news.aikoreacommunity.com/ai-native-company-yc-token-maxing-1000x-engineer/#/feedback/69f1e380602e450001e3325e/0/?uuid=9823a680-7a06-429b-8908-3cbd4bf03e7d&amp;key=3979968e61bafb918ec3c736e13c83f9f3e66de65fa4fd7d1d62e41009bef050\" target=\"_blank\" style=\"color: #45e600; text-decoration: none; overflow-wrap: anywhere;\">\r\n                                                            <img src=\"https://static.ghost.org/v5.0.0/images/less-like-this-mobile.png\" border=\"0\" width=\"42\" height=\"42\" alt=\"Less like this\" style=\"border: none; -ms-interpolation-mode: bicubic; max-width: 100%; display: block; margin: 0 auto; vertical-align: middle;\">\r\n                                                            <p class=\"feedback-button-text\" style=\"display: inline-block; font-family: -apple-system, BlinkMacSystemFont, Roboto, Helvetica, Arial, sans-serif; color: #15212A; font-weight: 500; margin: 1em 0 0 0; line-height: 1.4; word-break: break-word; font-size: 13px;\">Less like this</p>\r\n                                                        </a>\r\n                                                    </td>\r\n                                                    <td dir=\"ltr\" valign=\"top\" align=\"center\" style=\"font-size: 18px; color: #15212A; display: inline-block; box-sizing: border-box; vertical-align: top; font-family: inherit; text-align: center; padding: 0 4px 4px; cursor: pointer; width: 33.33%;\" width=\"33.33%\">\r\n                                                        <a href=\"https://news.aikoreacommunity.com/r/f57c2089?m=9823a680-7a06-429b-8908-3cbd4bf03e7d\" target=\"_blank\" style=\"color: #45e600; text-decoration: none; overflow-wrap: anywhere;\">\r\n                                                            <img src=\"https://static.ghost.org/v5.0.0/images/comment-mobile.png\" border=\"0\" width=\"42\" height=\"42\" alt=\"Comment\" style=\"border: none; -ms-interpolation-mode: bicubic; max-width: 100%; display: block; margin: 0 auto; vertical-align: middle;\">\r\n                                                            <p class=\"feedback-button-text\" style=\"display: inline-block; font-family: -apple-system, BlinkMacSystemFont, Roboto, Helvetica, Arial, sans-serif; color: #15212A; font-weight: 500; margin: 1em 0 0 0; line-height: 1.4; word-break: break-word; font-size: 13px;\">Comment</p>\r\n                                                        </a>\r\n                                                    </td>\r\n                                            </tr>\r\n                                        </table>\r\n                                    </td>\r\n                                </tr>\r\n\r\n                                <tr>\r\n                                    <td class=\"latest-posts-container\" style=\"font-family: -apple-system, BlinkMacSystemFont, Roboto, Helvetica, Arial, sans-serif; font-size: 18px; vertical-align: top; color: #15212A; padding: 24px 0; border-bottom: 1px solid #e0e7eb;\" valign=\"top\">\r\n                                        <h3 class=\"latest-posts-header\" style=\"margin-top: 0; line-height: 1.11; text-rendering: optimizeLegibility; margin: 0; padding: 8px 0 8px; color: #15212A; font-family: -apple-system, BlinkMacSystemFont, Roboto, Helvetica, Arial, sans-serif; font-size: 13px; font-weight: 600; text-transform: uppercase;\">Keep reading</h3>\r\n                                            <table role=\"presentation\" border=\"0\" cellpadding=\"0\" cellspacing=\"0\" style=\"border-collapse: separate; mso-table-lspace: 0pt; mso-table-rspace: 0pt; width: 100%;\" width=\"100%\">\r\n                                                <tr>\r\n                                                    <td class=\"latest-post\" style=\"font-family: -apple-system, BlinkMacSystemFont, Roboto, Helvetica, Arial, sans-serif; font-size: 18px; vertical-align: top; color: #15212A; padding: 16px 0; max-width: 600px;\" valign=\"top\">\r\n                                                        <table role=\"presentation\" border=\"0\" cellpadding=\"0\" cellspacing=\"0\" style=\"border-collapse: separate; mso-table-lspace: 0pt; mso-table-rspace: 0pt; width: 100%;\" width=\"100%\">\r\n                                                            <tr>\r\n                                                                <td valign=\"top\" align=\"left\" class=\"latest-post-title\" style=\"font-family: -apple-system, BlinkMacSystemFont, Roboto, Helvetica, Arial, sans-serif; font-size: 18px; vertical-align: top; color: #15212A; padding-right: 12px;\">\r\n                                                                    <h4 class style=\"margin-top: 0; font-family: -apple-system, BlinkMacSystemFont, Roboto, Helvetica, Arial, sans-serif; text-rendering: optimizeLegibility; line-height: 1.2; margin: 0; padding: 2px 0 4px; font-size: 18px; font-weight: 700; color: #15212A;\">\r\n                                                                        <a href=\"https://news.aikoreacommunity.com/r/ed2b49c5?m=9823a680-7a06-429b-8908-3cbd4bf03e7d\" style=\"overflow-wrap: anywhere; text-decoration: none; color: #15212A;\" target=\"_blank\">AI&#xB85C; &#xAC00;&#xC7A5; &#xC0AC;&#xC2E4;&#xC801;&#xC778; UGC &#xC601;&#xC0C1; &#xB9CC;&#xB4DC;&#xB294; &#xD301; (&#xD504;&#xB86C;&#xD504;&#xD2B8;)</a>\r\n                                                                    </h4>\r\n                                                                        <p class=\"latest-post-excerpt\" style=\"line-height: 1.6; margin: 0; padding: 0; font-size: 15px; font-weight: 400; color: #15212a; color: rgba(0, 0, 0, 0.6);\">\r\n                                                                            <a href=\"https://news.aikoreacommunity.com/r/b8986278?m=9823a680-7a06-429b-8908-3cbd4bf03e7d\" style=\"overflow-wrap: anywhere; text-decoration: none; color: #15212a; color: rgba(0, 0, 0, 0.6);\" target=\"_blank\">&#xC548;&#xB155;&#xD558;&#xC138;&#xC694;. &#xC5D0;&#xCF54; &#xBA64;&#xBC84;&#xB2D8;&#xB4E4;\r\n                                        \r\n                                        2023&#xB144;&#xBD80;&#xD130; AI &#xC601;&#xC0C1;&#xC744; &#xC811;&#xD558;&#xBA74;&#xC11C; &#xC815;&#xB9D0; &#xB9CE;&#xC740; &#xC601;&#xC0C1;&#xB4E4;&#xC744; &#xC800;&#xB294; &#xBCF8;&#xC5C5;&#xC778; &#xC544;&#xB9C8;&#xC874;&#xC5D0;&#xC11C; &#xC81C;&#xD488;&#xD310;&#xB9E4;&#xC5D0; &#xC140;&#xB7EC;&#xB4E4;&#xC774; &#xD65C;&#xC6A9;&#xD560; &#xC218; &#xC5C6;&#xC744;&#xAE4C;? &#xB77C;&#xB294; &#xC0DD;&#xAC01;&#xC73C;&#xB85C;<span class=\"desktop-only\"> &#xB9CC;&#xB4E4;&#xC5B4;&#xBD24;&#xC2B5;&#xB2C8;&#xB2E4;. &#xD2B9;&#xD788; UGC &#xC601;&#xC0C1;&#xB4E4;&#xC744; &#xB9CC;&#xB4E4;&#xAE30; &#xC704;&#xD574;&#xC11C; </span>&#x2026;</a>\r\n                                                                        </p>\r\n                                                                </td>\r\n                                                                        <td width=\"100\" class=\"latest-post-img\" style=\"font-family: -apple-system, BlinkMacSystemFont, Roboto, Helvetica, Arial, sans-serif; font-size: 18px; vertical-align: top; color: #15212A;\" valign=\"top\">\r\n                                                                            <a href=\"https://news.aikoreacommunity.com/r/2b0ec860?m=9823a680-7a06-429b-8908-3cbd4bf03e7d\" style=\"overflow-wrap: anywhere; display: block; height: 100px; overflow: hidden; color: inherit; text-decoration: none;\" target=\"_blank\">\r\n                                                                                <img src=\"https://storage.ghost.io/c/e1/33/e133371d-f862-4a59-b7a9-037bf2e0322c/content/images/size/w200h200/2026/04/AI-UGC-------------.png\" width=\"100\" height=\"100\" style=\"border: none; -ms-interpolation-mode: bicubic; max-width: 100%; object-fit: cover;\">\r\n                                                                            </a>\r\n                                                                        </td>\r\n                                                            </tr>\r\n                                                        </table>\r\n                                                    </td>\r\n                                                </tr>\r\n                                            </table>\r\n                                            <table role=\"presentation\" border=\"0\" cellpadding=\"0\" cellspacing=\"0\" style=\"border-collapse: separate; mso-table-lspace: 0pt; mso-table-rspace: 0pt; width: 100%;\" width=\"100%\">\r\n                                                <tr>\r\n                                                    <td class=\"latest-post\" style=\"font-family: -apple-system, BlinkMacSystemFont, Roboto, Helvetica, Arial, sans-serif; font-size: 18px; vertical-align: top; color: #15212A; padding: 16px 0; max-width: 600px;\" valign=\"top\">\r\n                                                        <table role=\"presentation\" border=\"0\" cellpadding=\"0\" cellspacing=\"0\" style=\"border-collapse: separate; mso-table-lspace: 0pt; mso-table-rspace: 0pt; width: 100%;\" width=\"100%\">\r\n                                                            <tr>\r\n                                                                <td valign=\"top\" align=\"left\" class=\"latest-post-title\" style=\"font-family: -apple-system, BlinkMacSystemFont, Roboto, Helvetica, Arial, sans-serif; font-size: 18px; vertical-align: top; color: #15212A; padding-right: 12px;\">\r\n                                                                    <h4 class style=\"margin-top: 0; font-family: -apple-system, BlinkMacSystemFont, Roboto, Helvetica, Arial, sans-serif; text-rendering: optimizeLegibility; line-height: 1.2; margin: 0; padding: 2px 0 4px; font-size: 18px; font-weight: 700; color: #15212A;\">\r\n                                                                        <a href=\"https://news.aikoreacommunity.com/r/7a6c5ca6?m=9823a680-7a06-429b-8908-3cbd4bf03e7d\" style=\"overflow-wrap: anywhere; text-decoration: none; color: #15212A;\" target=\"_blank\">GPT-5.5&#xAC00; &#xB358;&#xC9C4; &#xC9C4;&#xC9DC; &#xC9C8;&#xBB38; &#x2014; &#xAC19;&#xC740; AI&#xB97C; &#xC368;&#xB3C4; &#xB204;&#xAD70;&#xAC00;&#xB294; 100&#xBC30;&#xC758; &#xACB0;&#xACFC;&#xB97C; &#xB9CC;&#xB4E0;&#xB2E4;</a>\r\n                                                                    </h4>\r\n                                                                        <p class=\"latest-post-excerpt\" style=\"line-height: 1.6; margin: 0; padding: 0; font-size: 15px; font-weight: 400; color: #15212a; color: rgba(0, 0, 0, 0.6);\">\r\n                                                                            <a href=\"https://news.aikoreacommunity.com/r/6f536efe?m=9823a680-7a06-429b-8908-3cbd4bf03e7d\" style=\"overflow-wrap: anywhere; text-decoration: none; color: #15212a; color: rgba(0, 0, 0, 0.6);\" target=\"_blank\">&#xC5D0;&#xCF54; &#xBA64;&#xBC84;&#xB2D8;&#xB4E4;,\r\n                                        \r\n                                        &#xC694;&#xC998; &#xC5B4;&#xB5BB;&#xAC8C; &#xC9C0;&#xB0B4;&#xACE0; &#xACC4;&#xC2E0;&#xAC00;&#xC694;? &#xC624;&#xB298;&#xC740; &#xC815;&#xB9D0; &#xD765;&#xBBF8;&#xB85C;&#xC6B4; &#xC778;&#xD130;&#xBDF0; &#xD55C; &#xD3B8;&#xC744; &#xC18C;&#xAC1C;&#xD574;&#xB4DC;&#xB9AC;&#xB824; &#xD569;&#xB2C8;&#xB2E4;. &#xCD5C;&#xADFC; OpenAI&#xC758; &#xC0AC;&#xC7A5;&#xC774;&#xC790; &#xACF5;&#xB3D9;&#xCC3D;&#xC5C5;&#xC790;&#xC778; Greg B<span class=\"desktop-only\">rockman&#xC774; Big Technology Podcas</span>&#x2026;</a>\r\n                                                                        </p>\r\n                                                                </td>\r\n                                                                        <td width=\"100\" class=\"latest-post-img\" style=\"font-family: -apple-system, BlinkMacSystemFont, Roboto, Helvetica, Arial, sans-serif; font-size: 18px; vertical-align: top; color: #15212A;\" valign=\"top\">\r\n                                                                            <a href=\"https://news.aikoreacommunity.com/r/9b924e68?m=9823a680-7a06-429b-8908-3cbd4bf03e7d\" style=\"overflow-wrap: anywhere; display: block; height: 100px; overflow: hidden; color: inherit; text-decoration: none;\" target=\"_blank\">\r\n                                                                                <img src=\"https://storage.ghost.io/c/e1/33/e133371d-f862-4a59-b7a9-037bf2e0322c/content/images/size/w200h200/2026/04/------.png\" width=\"100\" height=\"100\" style=\"border: none; -ms-interpolation-mode: bicubic; max-width: 100%; object-fit: cover;\">\r\n                                                                            </a>\r\n                                                                        </td>\r\n                                                            </tr>\r\n                                                        </table>\r\n                                                    </td>\r\n                                                </tr>\r\n                                            </table>\r\n                                            <table role=\"presentation\" border=\"0\" cellpadding=\"0\" cellspacing=\"0\" style=\"border-collapse: separate; mso-table-lspace: 0pt; mso-table-rspace: 0pt; width: 100%;\" width=\"100%\">\r\n                                                <tr>\r\n                                                    <td class=\"latest-post\" style=\"font-family: -apple-system, BlinkMacSystemFont, Roboto, Helvetica, Arial, sans-serif; font-size: 18px; vertical-align: top; color: #15212A; padding: 16px 0; max-width: 600px;\" valign=\"top\">\r\n                                                        <table role=\"presentation\" border=\"0\" cellpadding=\"0\" cellspacing=\"0\" style=\"border-collapse: separate; mso-table-lspace: 0pt; mso-table-rspace: 0pt; width: 100%;\" width=\"100%\">\r\n                                                            <tr>\r\n                                                                <td valign=\"top\" align=\"left\" class=\"latest-post-title\" style=\"font-family: -apple-system, BlinkMacSystemFont, Roboto, Helvetica, Arial, sans-serif; font-size: 18px; vertical-align: top; color: #15212A; padding-right: 12px;\">\r\n                                                                    <h4 class style=\"margin-top: 0; font-family: -apple-system, BlinkMacSystemFont, Roboto, Helvetica, Arial, sans-serif; text-rendering: optimizeLegibility; line-height: 1.2; margin: 0; padding: 2px 0 4px; font-size: 18px; font-weight: 700; color: #15212A;\">\r\n                                                                        <a href=\"https://news.aikoreacommunity.com/r/c2123462?m=9823a680-7a06-429b-8908-3cbd4bf03e7d\" style=\"overflow-wrap: anywhere; text-decoration: none; color: #15212A;\" target=\"_blank\">AI&#xAC00; &#xBAA8;&#xB4E0; &#xAC83;&#xC744; &#xBCA0;&#xB07C;&#xB294; &#xC2DC;&#xB300;, &#xB2F9;&#xC2E0;&#xC5D0;&#xAC8C; &#xB0A8;&#xC740; &#xC9C4;&#xC9DC; &#xBB34;&#xAE30;&#xB294; &#xBB34;&#xC5C7;&#xC785;&#xB2C8;&#xAE4C;?</a>\r\n                                                                    </h4>\r\n                                                                        <p class=\"latest-post-excerpt\" style=\"line-height: 1.6; margin: 0; padding: 0; font-size: 15px; font-weight: 400; color: #15212a; color: rgba(0, 0, 0, 0.6);\">\r\n                                                                            <a href=\"https://news.aikoreacommunity.com/r/ebe19389?m=9823a680-7a06-429b-8908-3cbd4bf03e7d\" style=\"overflow-wrap: anywhere; text-decoration: none; color: #15212a; color: rgba(0, 0, 0, 0.6);\" target=\"_blank\">&#xC5D0;&#xCF54; &#xBA64;&#xBC84;&#xB2D8;&#xB4E4;,\r\n                                        &#xC798; &#xC9C0;&#xB0B4;&#xACE0; &#xACC4;&#xC2E0;&#xAC00;&#xC694;? &#xBCF4;&#xD45C;&#xC785;&#xB2C8;&#xB2E4;.\r\n                                        \r\n                                        &#xC624;&#xB298;&#xC740; &#xB2E8;&#xC21C;&#xD55C; AI &#xB274;&#xC2A4;&#xAC00; &#xC544;&#xB2D9;&#xB2C8;&#xB2E4;.\r\n                                        &#xADF8;&#xB9AC;&#xACE0; &#xB2E8;&#xC21C;&#xD55C; CEO &#xC778;&#xD130;&#xBDF0; &#xC694;&#xC57D;&#xB3C4; &#xC544;&#xB2D9;&#xB2C8;&#xB2E4;.\r\n                                        \r\n                                        &#xC624;&#xB298; &#xC774;&#xC57C;&#xAE30;&#xB294; &#xC55E;&#xC73C;&#xB85C; <span class=\"desktop-only\">&#xBA87; &#xB144; &#xB3D9;&#xC548; &#xC6B0;&#xB9AC;&#xAC00; &#xC77C;&#xC744; &#xD558;&#xACE0;, &#xCF58;&#xD150;&#xCE20;&#xB97C; &#xB9CC;&#xB4E4;&#xACE0;, &#xC0AC;&#xC5C5;</span>&#x2026;</a>\r\n                                                                        </p>\r\n                                                                </td>\r\n                                                                        <td width=\"100\" class=\"latest-post-img\" style=\"font-family: -apple-system, BlinkMacSystemFont, Roboto, Helvetica, Arial, sans-serif; font-size: 18px; vertical-align: top; color: #15212A;\" valign=\"top\">\r\n                                                                            <a href=\"https://news.aikoreacommunity.com/r/fac354c3?m=9823a680-7a06-429b-8908-3cbd4bf03e7d\" style=\"overflow-wrap: anywhere; display: block; height: 100px; overflow: hidden; color: inherit; text-decoration: none;\" target=\"_blank\">\r\n                                                                                <img src=\"https://storage.ghost.io/c/e1/33/e133371d-f862-4a59-b7a9-037bf2e0322c/content/images/size/w200h200/2026/04/----------------1.png\" width=\"100\" height=\"100\" style=\"border: none; -ms-interpolation-mode: bicubic; max-width: 100%; object-fit: cover;\">\r\n                                                                            </a>\r\n                                                                        </td>\r\n                                                            </tr>\r\n                                                        </table>\r\n                                                    </td>\r\n                                                </tr>\r\n                                            </table>\r\n                                    </td>\r\n                                </tr>\r\n\r\n                                <tr>\r\n                                    <td class=\"subscription-box\" style=\"font-family: -apple-system, BlinkMacSystemFont, Roboto, Helvetica, Arial, sans-serif; font-size: 18px; vertical-align: top; padding: 32px 0; border-bottom: 1px solid #e0e7eb; color: #15212A;\" valign=\"top\">\r\n                                        <h3 style=\"margin-top: 0; line-height: 1.11; text-rendering: optimizeLegibility; font-family: -apple-system, BlinkMacSystemFont, Roboto, Helvetica, Arial, sans-serif; font-size: 14px; font-weight: 600; text-transform: uppercase; margin: 0 0 18px;\">Subscription details</h3>\r\n                                        <p style=\"margin: 0 0 1.5em 0; font-size: 15px; font-weight: 400; line-height: 1.45; text-decoration: none; margin-bottom: 16px; color: #15212A;\">\r\n                                            <span>You are receiving this because you are a <strong style=\"font-weight: 700;\">free subscriber</strong> to AI &#xCF54;&#xB9AC;&#xC544; &#xCEE4;&#xBBA4;&#xB2C8;&#xD2F0; &#xB274;&#xC2A4;&#xB808;&#xD130;.</span> \r\n                                        </p>\r\n                                        <table role=\"presentation\" border=\"0\" cellpadding=\"0\" cellspacing=\"0\" width=\"100%\" style=\"border-collapse: separate; mso-table-lspace: 0pt; mso-table-rspace: 0pt; width: 100%;\">\r\n                                            <tr>\r\n                                                <td class=\"subscription-details\" style=\"font-family: -apple-system, BlinkMacSystemFont, Roboto, Helvetica, Arial, sans-serif; font-size: 18px; vertical-align: top; color: #15212A;\" valign=\"top\">\r\n                                                    <p class=\"hidden\" style=\"margin: 0 0 1.5em 0; margin-bottom: 0; font-size: 15px; font-weight: 400; line-height: 1.45; text-decoration: none; color: #15212A;\">Name: not provided</p>\r\n                                                    <p style=\"margin: 0 0 1.5em 0; margin-bottom: 0; font-size: 15px; font-weight: 400; line-height: 1.45; text-decoration: none; color: #15212A;\">Email: <a href=\"#\" style=\"overflow-wrap: anywhere; text-decoration: none; color: #15212A;\" target=\"_blank\">sungyoon5450@naver.com</a></p>\r\n                                                    <p style=\"margin: 0 0 1.5em 0; margin-bottom: 0; font-size: 15px; font-weight: 400; line-height: 1.45; text-decoration: none; color: #15212A;\">Member since: 29 April 2024</p>\r\n                                                </td>\r\n                                                <td align=\"right\" valign=\"bottom\" class=\"manage-subscription\" style=\"font-family: -apple-system, BlinkMacSystemFont, Roboto, Helvetica, Arial, sans-serif; color: #15212A; font-size: 15px; font-weight: 400; text-align: right; line-height: 1.45; vertical-align: bottom;\">\r\n                                                    <a href=\"https://news.aikoreacommunity.com/#/portal/account\" style=\"overflow-wrap: anywhere; text-decoration: underline; color: #45e600;\" target=\"_blank\"> Manage subscription</a>\r\n                                                </td>\r\n                                            </tr>\r\n                                        </table>\r\n                                    </td>\r\n                                </tr>\r\n\r\n                            <tr>\r\n                                <td class=\"wrapper\" align=\"center\" style=\"font-family: -apple-system, BlinkMacSystemFont, Roboto, Helvetica, Arial, sans-serif; font-size: 18px; vertical-align: top; color: #15212A; box-sizing: border-box;\" valign=\"top\">\r\n                                    <table role=\"presentation\" border=\"0\" cellpadding=\"0\" cellspacing=\"0\" width=\"100%\" style=\"border-collapse: separate; mso-table-lspace: 0pt; mso-table-rspace: 0pt; width: 100%; padding-top: 40px; padding-bottom: 30px;\">\r\n                                        <tr>\r\n                                            <td class=\"footer\" style=\"font-family: -apple-system, BlinkMacSystemFont, Roboto, Helvetica, Arial, sans-serif; vertical-align: top; color: #15212a; color: rgba(0, 0, 0, 0.6); margin-top: 20px; text-align: center; padding-bottom: 10px; padding-top: 10px; padding-left: 30px; padding-right: 30px; line-height: 1.5; font-size: 13px;\" valign=\"top\" align=\"center\">AI &#xCF54;&#xB9AC;&#xC544; &#xCEE4;&#xBBA4;&#xB2C8;&#xD2F0; &#xB274;&#xC2A4;&#xB808;&#xD130; &#xA9; 2026 &#x2013; <a href=\"https://news.aikoreacommunity.com/unsubscribe/?uuid=9823a680-7a06-429b-8908-3cbd4bf03e7d&key=3979968e61bafb918ec3c736e13c83f9f3e66de65fa4fd7d1d62e41009bef050&newsletter=e39a95d1-5c29-4320-ade2-4b8adfb21adc\" style=\"overflow-wrap: anywhere; color: #15212a; color: rgba(0, 0, 0, 0.6); text-decoration: underline; font-size: 13px;\" target=\"_blank\">Unsubscribe</a></td>\r\n                                        </tr>\r\n\r\n                                    </table>\r\n                                </td>\r\n                            </tr>\r\n</table>\r\n                        <!-- END CENTERED WHITE CONTAINER -->\r\n                    </div>\r\n                </td>\r\n                <td style=\"font-family: -apple-system, BlinkMacSystemFont, Roboto, Helvetica, Arial, sans-serif; font-size: 18px; vertical-align: top; color: #15212A;\" valign=\"top\">&#xA0;</td>\r\n            </tr>\r\n\r\n            <!--[if mso]>\r\n                            </table>\r\n                        </center>\r\n                    </td>\r\n                </tr>\r\n            <![endif]-->\r\n        </table>\r\n    </body>\r\n</html>\r\n\r\n"
}